{"bones":[{"name":"root","x":-4.12,"scaleX":1.4,"scaleY":1.4},{"name":"hip","parent":"root","x":-5.41,"y":271.15},{"name":"leftUpperLeg","parent":"hip","length":105.44,"x":-3.23,"y":-4.27,"rotation":-88.06},{"name":"rightUpperLeg","parent":"hip","length":108.3,"x":-9.85,"y":-5.69,"rotation":-85.12},{"name":"spine","parent":"hip","length":148.2,"x":-1.42,"y":11.4,"rotation":89.35},{"name":"leftLowerLeg","parent":"leftUpperLeg","length":109.95,"x":118.05,"y":1.01,"rotation":-2.52},{"name":"leftUpperArm","parent":"spine","length":90.99,"x":128.1,"y":7.7,"rotation":-177.31},{"name":"neck","parent":"spine","length":24.59,"x":151.03,"y":2.61,"rotation":-9.38},{"name":"rightLowerLeg","parent":"rightUpperLeg","length":111.19,"x":119.76,"y":-0.87,"rotation":-6.5},{"name":"rightUpperArm","parent":"spine","length":79.94,"x":127.45,"y":27.14,"rotation":-172.18},{"name":"head","parent":"neck","length":41.91,"x":27.65,"y":-0.99,"rotation":-7.68},{"name":"leftFoot","parent":"leftLowerLeg","length":47.11,"x":136.81,"y":-1.67,"rotation":87.35},{"name":"leftLowerArm","parent":"leftUpperArm","length":68.53,"x":95.38,"y":0.86,"rotation":-1.33},{"name":"rightFoot","parent":"rightLowerLeg","length":48.63,"x":134.71,"y":-0.38,"rotation":89.09},{"name":"rightLowerArm","parent":"rightUpperArm","length":77.66,"x":96.58,"y":-2.45,"rotation":3.02},{"name":"leftHand","parent":"leftLowerArm","length":23.58,"x":95,"y":0.1,"rotation":7.57},{"name":"rightHand","parent":"rightLowerArm","length":27.22,"x":89.18,"y":-2.14,"rotation":1.48}],"slots":[{"name":"left closed hand","bone":"leftHand","attachment":"left_closed_hand"},{"name":"left lower arm","bone":"leftLowerArm","attachment":"left_lower_arm"},{"name":"left upper arm","bone":"leftUpperArm","attachment":"left_upper_arm"},{"name":"left hooked arm","bone":"leftUpperArm"},{"name":"backJacket","bone":"spine","attachment":"back_torso"},{"name":"neck","bone":"neck","attachment":"_neck"},{"name":"head","bone":"head","attachment":"_head"},{"name":"left lower leg","bone":"leftLowerLeg","attachment":"left_lower_leg"},{"name":"left shoe","bone":"leftFoot","attachment":"left_shoe"},{"name":"left upper leg","bone":"leftUpperLeg","attachment":"left_upper_leg"},{"name":"right lower leg","bone":"rightLowerLeg","attachment":"right_lower_leg"},{"name":"right shoe","bone":"rightFoot","attachment":"right_shoe"},{"name":"right upper leg","bone":"rightUpperLeg","attachment":"right_upper_leg"},{"name":"right open hand","bone":"rightHand"},{"name":"torso","bone":"spine","attachment":"_torso"},{"name":"right closed hand","bone":"rightHand","attachment":"right_closed_hand"},{"name":"right lower arm","bone":"rightLowerArm","attachment":"right_lower_arm"},{"name":"right upper arm","bone":"rightUpperArm","attachment":"right_upper_arm"},{"name":"right hooked arm","bone":"rightUpperArm"}],"skins":{"color":{"backJacket":{"back_torso":{"name":"back torso","x":67.42,"y":-18.2,"rotation":-88.4,"width":59,"height":198}},"head":{"_head":{"name":"head","x":17.83,"y":8.5,"rotation":-72.47,"width":74,"height":76}},"left closed hand":{"left_closed_hand":{"name":"left closed hand","x":13.05,"y":2.06,"rotation":65.35,"width":34,"height":50}},"left hooked arm":{"left_hooked_arm":{"name":"left hooked arm","path":"hooked arm","x":66.83,"y":-3.27,"rotation":-115.77,"width":117,"height":130}},"left lower arm":{"left_lower_arm":{"name":"left lower arm","x":36.71,"y":1.63,"rotation":86.84,"width":46,"height":110}},"left lower leg":{"left_lower_leg":{"name":"left lower leg","x":52.42,"y":-1.34,"rotation":93.6,"width":54,"height":148}},"left shoe":{"left_shoe":{"name":"left shoe","x":13.19,"y":13.56,"rotation":3.6,"width":75,"height":45}},"left upper arm":{"left_upper_arm":{"name":"left upper arm","x":50.86,"y":3.48,"rotation":93.17,"width":49,"height":126}},"left upper leg":{"left_upper_leg":{"name":"left upper leg","x":59.52,"y":1.39,"rotation":90,"width":65,"height":157}},"neck":{"_neck":{"name":"neck","x":15.98,"y":-3.06,"rotation":-80.15,"width":50,"height":62}},"right closed hand":{"right_closed_hand":{"name":"right closed hand","x":12.06,"y":1.91,"rotation":85.25,"width":34,"height":51}},"right hooked arm":{"right_hooked_arm":{"name":"right hooked arm","x":64.74,"y":3.07,"rotation":-116.94,"width":96,"height":142}},"right lower arm":{"right_lower_arm":{"name":"right lower arm","x":37.9,"y":0.37,"rotation":85.87,"width":46,"height":109}},"right lower leg":{"right_lower_leg":{"name":"right lower leg","x":53.16,"y":-0.69,"rotation":94.08,"width":54,"height":148}},"right open hand":{"right_open_hand":{"name":"right open hand","x":22.91,"y":3.92,"rotation":85.81,"width":40,"height":70}},"right shoe":{"right_shoe":{"name":"right shoe","x":14.54,"y":11.16,"rotation":4.98,"width":75,"height":45}},"right upper arm":{"right_upper_arm":{"name":"right upper arm","x":51.01,"y":1.02,"rotation":90.61,"width":48,"height":126}},"right upper leg":{"right_upper_leg":{"name":"right upper leg","x":52.11,"rotation":89.54,"width":67,"height":158}},"torso":{"_torso":{"name":"torso","x":64.69,"y":8.89,"rotation":-89.54,"width":88,"height":214}}},"silhouette":{"backJacket":{"back_torso":{"name":"silhouette/back torso","x":68.04,"y":-17.02,"rotation":-89.35,"width":58,"height":194}},"head":{"_head":{"name":"silhouette/head","x":18.96,"y":7.68,"rotation":-72.29,"width":74,"height":76}},"left closed hand":{"left_closed_hand":{"name":"silhouette/left closed hand","x":8.3,"y":1.76,"rotation":81.21,"width":33,"height":49}},"left hooked arm":{"left_hooked_arm":{"name":"silhouette/hooked arm","x":70.23,"y":-1.46,"rotation":-116.45,"width":116,"height":129}},"left lower arm":{"left_lower_arm":{"name":"silhouette/left lower arm","x":37.88,"y":-4.8,"rotation":88.78,"width":45,"height":107}},"left lower leg":{"left_lower_leg":{"name":"silhouette/left lower leg","x":66.74,"y":-9.09,"rotation":90.57,"width":54,"height":148}},"left shoe":{"left_shoe":{"name":"silhouette/left shoe","x":4.72,"y":5.13,"rotation":3.22,"width":74,"height":45}},"left upper arm":{"left_upper_arm":{"name":"silhouette/left upper arm","x":56.8,"y":0.6,"rotation":88.32,"width":48,"height":124}},"left upper leg":{"left_upper_leg":{"name":"silhouette/left upper leg","x":63.76,"y":-1.83,"rotation":88.06,"width":65,"height":157}},"neck":{"_neck":{"name":"silhouette/neck","x":19.04,"y":-1.94,"rotation":-79.97,"width":50,"height":62}},"right closed hand":{"right_closed_hand":{"name":"silhouette/right closed hand","x":15.65,"y":-2.01,"rotation":85.81,"width":34,"height":51}},"right hooked arm":{"right_hooked_arm":{"name":"silhouette/right hooked arm","x":69.12,"y":1.44,"rotation":-124.76,"width":95,"height":140}},"right lower arm":{"right_lower_arm":{"name":"silhouette/right lower arm","x":35.98,"y":-2.18,"rotation":83.04,"width":43,"height":109}},"right lower leg":{"right_lower_leg":{"name":"silhouette/right lower leg","x":58.6,"y":-6.36,"rotation":91.62,"width":54,"height":148}},"right open hand":{"right_open_hand":{"name":"silhouette/right open hand","x":-89.68,"y":-9.97,"rotation":85.81,"width":39,"height":68}},"right shoe":{"right_shoe":{"name":"silhouette/right shoe","x":0.9,"y":4.61,"rotation":2.53,"width":74,"height":45}},"right upper arm":{"right_upper_arm":{"name":"silhouette/right upper arm","x":44.99,"y":2.85,"rotation":90.31,"width":49,"height":124}},"right upper leg":{"right_upper_leg":{"name":"silhouette/right upper leg","x":67.06,"y":-2.67,"rotation":85.12,"width":66,"height":155}},"torso":{"_torso":{"name":"silhouette/torso","x":69.39,"y":6.66,"rotation":-89.35,"width":87,"height":212}}}},"animations":{"climbUp":{"bones":{"leftUpperArm":{"rotate":[{"time":0,"angle":158.08},{"time":0.1666,"angle":98.22},{"time":0.3333,"angle":62.78},{"time":0.6666,"angle":50.86},{"time":1.3333,"angle":23.99},{"time":1.5,"angle":-0.17}],"translate":[{"time":0,"x":-19.49,"y":2.46},{"time":1.5,"x":-1.37,"y":9.84}]},"rightUpperArm":{"rotate":[{"time":0,"angle":156.01},{"time":0.1666,"angle":92.47},{"time":0.3333,"angle":57.03},{"time":0.6666,"angle":58.76},{"time":0.8333,"angle":29.22},{"time":1.3333,"angle":359.21},{"time":1.5,"angle":-0.17}],"translate":[{"time":0,"x":-19.49,"y":2.46},{"time":1.5,"x":-0.99,"y":-0.47}]},"rightHand":{"rotate":[{"time":1.5,"angle":-0.17}]},"head":{"rotate":[{"time":0,"angle":34.26},{"time":0.3333,"angle":-8.1},{"time":1.5,"angle":-0.17}]},"leftLowerArm":{"rotate":[{"time":0,"angle":16.45},{"time":0.1666,"angle":84.8},{"time":0.3333,"angle":102.82},{"time":0.6666,"angle":16.57},{"time":0.8333,"angle":32.2},{"time":1.5,"angle":-0.17}]},"rightLowerArm":{"rotate":[{"time":0,"angle":16.34},{"time":0.1666,"angle":89.83},{"time":0.3333,"angle":111.17},{"time":0.6666,"angle":7.01},{"time":0.8333,"angle":45.09},{"time":1.5,"angle":-0.17}]},"leftUpperLeg":{"rotate":[{"time":0,"angle":7.04},{"time":0.1,"angle":63.5},{"time":0.1666,"angle":52.93},{"time":0.3333,"angle":102.12},{"time":0.6666,"angle":110.65},{"time":1.1666,"angle":109.88},{"time":1.3333,"angle":83.04},{"time":1.5,"angle":-0.17}]},"rightUpperLeg":{"rotate":[{"time":0,"angle":-6.83},{"time":0.1666,"angle":21.46},{"time":0.3333,"angle":65.54},{"time":0.6666,"angle":115.93},{"time":1,"angle":139.58},{"time":1.1666,"angle":130.16},{"time":1.3333,"angle":89.9},{"time":1.5,"angle":-0.17}]},"leftLowerLeg":{"rotate":[{"time":0,"angle":-22.47},{"time":0.1,"angle":-73.39},{"time":0.1666,"angle":-79.27},{"time":0.3333,"angle":-78.36},{"time":0.5,"angle":-126.27},{"time":0.6666,"angle":-126.24},{"time":0.8333,"angle":-109.93},{"time":1,"angle":-106.43},{"time":1.1666,"angle":-106.08},{"time":1.3333,"angle":-44.15},{"time":1.5,"angle":-0.17}]},"rightLowerLeg":{"rotate":[{"time":0,"angle":-8.14},{"time":0.1666,"angle":-53.19},{"time":0.3333,"angle":-30.31},{"time":0.5,"angle":-108.68},{"time":0.6666,"angle":-114.6},{"time":1,"angle":-83.74},{"time":1.3333,"angle":-33.46},{"time":1.5,"angle":-0.17}]},"hip":{"rotate":[{"time":0.1666,"angle":-1.16},{"time":0.3333,"angle":-12.56},{"time":0.5,"angle":-34.96},{"time":0.6666,"angle":-36.73},{"time":1,"angle":-59.57},{"time":1.3333,"angle":-70.28},{"time":1.5,"angle":-0.17}],"translate":[{"time":0,"x":60.87,"y":-17.64},{"time":0.1666,"x":-4.86,"y":81.68},{"time":0.3333,"x":-51.19,"y":198.36},{"time":0.5,"x":-51.19,"y":328.48},{"time":0.6666,"x":-6.39,"y":443.23},{"time":0.8333,"x":83.18,"y":482.05},{"time":1,"x":115.18,"y":458.59},{"time":1.1666,"x":132.24,"y":469.26},{"time":1.3333,"x":150.48,"y":553.78},{"time":1.5,"x":176.03,"y":571.14}]},"rightFoot":{"rotate":[{"time":0,"angle":-1.77},{"time":1,"angle":-1.99},{"time":1.1666,"angle":7.06},{"time":1.5,"angle":-0.17}]},"leftFoot":{"rotate":[{"time":0,"angle":1.72},{"time":1,"angle":38.8},{"time":1.1666,"angle":19.01},{"time":1.5,"angle":-0.17}]},"spine":{"rotate":[{"time":0,"angle":-1.78},{"time":0.3333,"angle":-22.53},{"time":1,"angle":1.27},{"time":1.1666,"angle":14.73},{"time":1.3333,"angle":42.57},{"time":1.5,"angle":-0.17}],"translate":[{"time":0.8333,"x":-8.47,"y":-0.03},{"time":1.5,"x":-3.24,"y":-4.25}]},"leftHand":{"rotate":[{"time":1.5,"angle":-0.17}]},"root":{"rotate":[{"time":1.5,"angle":-0.17}],"translate":[{"time":1.5,"x":-2.65,"y":0}]},"neck":{"rotate":[{"time":1.5,"angle":-0.17}]}},"slots":{"left hooked arm":{"attachment":[{"time":0,"name":null},{"time":1.5,"name":null}]},"right hooked arm":{"attachment":[{"time":0,"name":null},{"time":1.5,"name":null}]},"right open hand":{"attachment":[{"time":0,"name":null}]}}},"falling":{"bones":{"hip":{"translate":[{"time":0,"x":0,"y":51.54,"curve":"stepped"},{"time":1.5,"x":0,"y":51.54}]},"leftUpperLeg":{"rotate":[{"time":0,"angle":63.4},{"time":0.1666,"angle":47.99},{"time":0.4666,"angle":41.43},{"time":0.6666,"angle":17.33},{"time":0.8333,"angle":48.84},{"time":1.0666,"angle":38.28},{"time":1.3666,"angle":65.17},{"time":1.5,"angle":63.4}]},"rightUpperLeg":{"rotate":[{"time":0,"angle":27.37},{"time":0.6,"angle":38.13},{"time":0.8333,"angle":52.04},{"time":1.0666,"angle":58.33},{"time":1.5,"angle":27.37}]},"leftLowerLeg":{"rotate":[{"time":0,"angle":-53.03},{"time":0.1666,"angle":-14.41},{"time":0.3333,"angle":-28.98},{"time":0.4666,"angle":-40.62},{"time":0.8333,"angle":-65.81},{"time":1.5,"angle":-53.03}]},"rightLowerLeg":{"rotate":[{"time":0,"angle":-53.36},{"time":0.1666,"angle":-40.38},{"time":0.3333,"angle":-30.38},{"time":0.4666,"angle":-24.1},{"time":1.5,"angle":-53.36}]},"leftUpperArm":{"rotate":[{"time":0,"angle":306.13},{"time":0.1,"angle":288.23},{"time":0.2333,"angle":219.56},{"time":0.3333,"angle":158.58},{"time":0.5666,"angle":46.82},{"time":0.6666,"angle":354.99},{"time":0.7666,"angle":306.11},{"time":0.8666,"angle":288.23},{"time":1,"angle":214.89},{"time":1.1,"angle":119.38},{"time":1.1666,"angle":53.05},{"time":1.3333,"angle":33.36},{"time":1.4333,"angle":306.13,"curve":"stepped"},{"time":1.5,"angle":306.13}]},"rightUpperArm":{"rotate":[{"time":0,"angle":305.51},{"time":0.1,"angle":291.61},{"time":0.2333,"angle":222.93},{"time":0.3333,"angle":161.95},{"time":0.5666,"angle":48.91},{"time":0.6666,"angle":357.08},{"time":0.7666,"angle":308.19},{"time":0.8666,"angle":291.61},{"time":1,"angle":218.27},{"time":1.1,"angle":122.75},{"time":1.1666,"angle":56.42},{"time":1.3333,"angle":36.73},{"time":1.4333,"angle":305.51,"curve":"stepped"},{"time":1.5,"angle":305.51}]},"leftLowerArm":{"rotate":[{"time":0,"angle":64.47},{"time":0.1,"angle":84.64},{"time":0.5666,"angle":74.45},{"time":1.1666,"angle":74.85},{"time":1.5,"angle":64.47}]},"rightLowerArm":{"rotate":[{"time":0,"angle":68.55},{"time":0.1,"angle":82.97},{"time":0.5666,"angle":81.59},{"time":1.1666,"angle":91.1},{"time":1.5,"angle":68.55}]},"spine":{"rotate":[{"time":0,"angle":-12.64},{"time":0.1666,"angle":-14.66},{"time":0.4666,"angle":-11.16},{"time":0.8333,"angle":-7.27},{"time":1.5,"angle":-12.64}]},"head":{"rotate":[{"time":0,"angle":-12.28,"curve":"stepped"},{"time":1.5,"angle":-12.28}]}},"slots":{"left closed hand":{"attachment":[{"time":0,"name":"left closed hand"},{"time":0.1,"name":null},{"time":0.5666,"name":"left_closed_hand"},{"time":0.8666,"name":null},{"time":1.1666,"name":"left_closed_hand"},{"time":1.5,"name":"left closed hand"}]},"left hooked arm":{"attachment":[{"time":0,"name":null},{"time":0.1,"name":"left_hooked_arm"},{"time":0.5666,"name":null},{"time":0.8666,"name":"left_hooked_arm"},{"time":1.1666,"name":null},{"time":1.4333,"name":null},{"time":1.5,"name":null}]},"left lower arm":{"attachment":[{"time":0,"name":"left lower arm"},{"time":0.1,"name":null},{"time":0.5666,"name":"left_lower_arm"},{"time":0.8666,"name":null},{"time":1.1666,"name":"left_lower_arm"},{"time":1.5,"name":"left lower arm"}]},"left upper arm":{"attachment":[{"time":0,"name":"left upper arm"},{"time":0.1,"name":null},{"time":0.5666,"name":"left_upper_arm"},{"time":0.8666,"name":null},{"time":1.1666,"name":"left_upper_arm"},{"time":1.4333,"name":"left upper arm"},{"time":1.5,"name":"left upper arm"}]},"right closed hand":{"attachment":[{"time":0.1,"name":null},{"time":0.5666,"name":"right_closed_hand"},{"time":0.8666,"name":null},{"time":1,"name":null},{"time":1.1666,"name":"right_closed_hand"}]},"right hooked arm":{"attachment":[{"time":0,"name":null},{"time":0.1,"name":"right_hooked_arm"},{"time":0.5666,"name":null},{"time":0.8666,"name":"right_hooked_arm"},{"time":1.1666,"name":null},{"time":1.4333,"name":null},{"time":1.5,"name":null}]},"right lower arm":{"attachment":[{"time":0.1,"name":null},{"time":0.5666,"name":"right_lower_arm"},{"time":0.8666,"name":null},{"time":1.1666,"name":"right_lower_arm"}]},"right open hand":{"attachment":[{"time":0,"name":null},{"time":0.1,"name":null},{"time":1.5,"name":null}]},"right upper arm":{"attachment":[{"time":0.1,"name":null},{"time":0.5666,"name":"right_upper_arm"},{"time":0.8666,"name":null},{"time":1.1666,"name":"right_upper_arm"}]}}},"hang":{"bones":{"leftUpperArm":{"rotate":[{"time":0,"angle":155.57,"curve":"stepped"},{"time":1.3333,"angle":155.57}],"translate":[{"time":0,"x":-16.34,"y":-0.18,"curve":"stepped"},{"time":1.3333,"x":-16.34,"y":-0.18}]},"rightUpperArm":{"rotate":[{"time":0,"angle":149.36,"curve":"stepped"},{"time":1.3333,"angle":149.36}],"translate":[{"time":0,"x":-16.34,"y":-0.18,"curve":"stepped"},{"time":1.3333,"x":-16.34,"y":-0.18}]},"head":{"rotate":[{"time":0,"angle":41.94},{"time":0.6666,"angle":17.59},{"time":1.3333,"angle":41.94}]},"leftLowerArm":{"rotate":[{"time":0,"angle":10.62,"curve":"stepped"},{"time":1.3333,"angle":10.62}]},"rightLowerArm":{"rotate":[{"time":0,"angle":16.06,"curve":"stepped"},{"time":1.3333,"angle":16.06}]},"leftUpperLeg":{"rotate":[{"time":0,"angle":2.23},{"time":0.1666,"angle":9.68},{"time":0.3333,"angle":-0.47},{"time":0.5,"angle":20.96},{"time":0.6666,"angle":-23.28},{"time":1,"angle":-28},{"time":1.3333,"angle":2.23}]},"rightUpperLeg":{"rotate":[{"time":0,"angle":-10.5},{"time":0.1666,"angle":11.43},{"time":0.5,"angle":22.71},{"time":0.6666,"angle":-4.45},{"time":1,"angle":-14.51},{"time":1.3333,"angle":-10.5}]},"leftLowerLeg":{"rotate":[{"time":0,"angle":-19.35},{"time":0.1666,"angle":-41.81},{"time":0.6666,"angle":-53.79},{"time":1.3333,"angle":-19.35}]},"rightLowerLeg":{"rotate":[{"time":0,"angle":-0.43},{"time":0.1666,"angle":-12.28},{"time":0.8333,"angle":-35.18},{"time":1.1666,"angle":-58.55},{"time":1.3333,"angle":-0.43}]},"hip":{"translate":[{"time":0,"x":47.09,"y":3.81,"curve":"stepped"},{"time":1.3333,"x":47.09,"y":3.81}]}},"slots":{"left hooked arm":{"attachment":[{"time":0,"name":null}]},"right hooked arm":{"attachment":[{"time":0,"name":null}]},"right open hand":{"attachment":[{"time":0,"name":null}]}}},"idle1":{"bones":{"root":{"rotate":[{"time":0,"angle":-0.17,"curve":"stepped"},{"time":1,"angle":-0.17,"curve":"stepped"},{"time":2,"angle":-0.17,"curve":"stepped"},{"time":3,"angle":-0.17,"curve":"stepped"},{"time":4,"angle":-0.17,"curve":"stepped"},{"time":6,"angle":-0.17,"curve":"stepped"},{"time":6.1666,"angle":-0.17,"curve":"stepped"},{"time":7,"angle":-0.17,"curve":"stepped"},{"time":8,"angle":-0.17,"curve":"stepped"},{"time":9,"angle":-0.17,"curve":"stepped"},{"time":9.6666,"angle":-0.17,"curve":"stepped"},{"time":10,"angle":-0.17,"curve":"stepped"},{"time":10.8333,"angle":-0.17,"curve":"stepped"},{"time":11.2,"angle":-0.17,"curve":"stepped"},{"time":11.8333,"angle":-0.17,"curve":"stepped"},{"time":12.6666,"angle":-0.17,"curve":"stepped"},{"time":13.6666,"angle":-0.17}],"translate":[{"time":0,"x":-2.65,"y":0,"curve":"stepped"},{"time":1,"x":-2.65,"y":0,"curve":"stepped"},{"time":2,"x":-2.65,"y":0,"curve":"stepped"},{"time":3,"x":-2.65,"y":0,"curve":"stepped"},{"time":4,"x":-2.65,"y":0,"curve":"stepped"},{"time":6,"x":-2.65,"y":0,"curve":"stepped"},{"time":6.1666,"x":-2.65,"y":0,"curve":"stepped"},{"time":7,"x":-2.65,"y":0,"curve":"stepped"},{"time":8,"x":-2.65,"y":0,"curve":"stepped"},{"time":9,"x":-2.65,"y":0,"curve":"stepped"},{"time":9.6666,"x":-2.65,"y":0,"curve":"stepped"},{"time":10,"x":-2.65,"y":0,"curve":"stepped"},{"time":10.8333,"x":-2.65,"y":0,"curve":"stepped"},{"time":11.2,"x":-2.65,"y":0,"curve":"stepped"},{"time":11.8333,"x":-2.65,"y":0,"curve":"stepped"},{"time":12.6666,"x":-2.65,"y":0,"curve":"stepped"},{"time":13.6666,"x":-2.65,"y":0}]},"hip":{"rotate":[{"time":0,"angle":-0.17,"curve":"stepped"},{"time":1,"angle":-0.17,"curve":"stepped"},{"time":2,"angle":-0.17,"curve":"stepped"},{"time":3,"angle":-0.17,"curve":"stepped"},{"time":4,"angle":-0.17,"curve":"stepped"},{"time":6,"angle":-0.17,"curve":"stepped"},{"time":6.1666,"angle":-0.17,"curve":"stepped"},{"time":7,"angle":-0.17,"curve":"stepped"},{"time":8,"angle":-0.17,"curve":"stepped"},{"time":9,"angle":-0.17,"curve":"stepped"},{"time":9.6666,"angle":-0.17,"curve":"stepped"},{"time":10,"angle":-0.17,"curve":"stepped"},{"time":10.8333,"angle":-0.17,"curve":"stepped"},{"time":11.2,"angle":-0.17,"curve":"stepped"},{"time":11.8333,"angle":-0.17,"curve":"stepped"},{"time":12.6666,"angle":-0.17,"curve":"stepped"},{"time":13.6666,"angle":-0.17}],"translate":[{"time":0,"x":0,"y":-1.34},{"time":2,"x":0.01,"y":-5.37},{"time":13.6666,"x":0,"y":-1.34}]},"leftUpperLeg":{"rotate":[{"time":0,"angle":1.66,"curve":"stepped"},{"time":0.6666,"angle":1.66,"curve":"stepped"},{"time":1,"angle":1.66},{"time":2,"angle":7.07},{"time":3,"angle":1.66,"curve":"stepped"},{"time":4,"angle":1.66,"curve":"stepped"},{"time":6,"angle":1.66,"curve":"stepped"},{"time":6.1666,"angle":1.66,"curve":"stepped"},{"time":7,"angle":1.66,"curve":"stepped"},{"time":8,"angle":1.66,"curve":"stepped"},{"time":9,"angle":1.66,"curve":"stepped"},{"time":9.6666,"angle":1.66,"curve":"stepped"},{"time":10,"angle":1.66,"curve":"stepped"},{"time":10.8333,"angle":1.66,"curve":"stepped"},{"time":11.2,"angle":1.66,"curve":"stepped"},{"time":11.8333,"angle":1.66,"curve":"stepped"},{"time":12.6666,"angle":1.66,"curve":"stepped"},{"time":13.6666,"angle":1.66}]},"rightUpperLeg":{"rotate":[{"time":0,"angle":-3.07,"curve":"stepped"},{"time":0.6666,"angle":-3.07,"curve":"stepped"},{"time":1,"angle":-3.07},{"time":2,"angle":-8.61},{"time":3,"angle":-3.07},{"time":4,"angle":-4.99},{"time":4.1666,"angle":-2.67},{"time":6,"angle":-3.07,"curve":"stepped"},{"time":6.1666,"angle":-3.07,"curve":"stepped"},{"time":7,"angle":-3.07,"curve":"stepped"},{"time":8,"angle":-3.07,"curve":"stepped"},{"time":9,"angle":-3.07,"curve":"stepped"},{"time":9.6666,"angle":-3.07},{"time":10,"angle":115.18,"curve":"stepped"},{"time":10.8333,"angle":115.18},{"time":11.2,"angle":-3.07,"curve":"stepped"},{"time":11.8333,"angle":-3.07,"curve":"stepped"},{"time":12.6666,"angle":-3.07,"curve":"stepped"},{"time":13.6666,"angle":-3.07}]},"spine":{"rotate":[{"time":0,"angle":-0.17,"curve":"stepped"},{"time":1,"angle":-0.17,"curve":"stepped"},{"time":2,"angle":-0.17,"curve":"stepped"},{"time":3,"angle":-0.17},{"time":3.6666,"angle":-0.45},{"time":4,"angle":6.61},{"time":4.1666,"angle":17.82,"curve":"stepped"},{"time":5.6666,"angle":17.82},{"time":5.8333,"angle":7.56},{"time":6,"angle":0.38},{"time":6.1666,"angle":-0.17,"curve":"stepped"},{"time":7,"angle":-0.17,"curve":"stepped"},{"time":8,"angle":-0.17,"curve":"stepped"},{"time":9,"angle":-0.17,"curve":"stepped"},{"time":9.6666,"angle":-0.17},{"time":10,"angle":4.81},{"time":10.3333,"angle":9.75},{"time":10.8333,"angle":4.81},{"time":11.2,"angle":-0.17,"curve":"stepped"},{"time":11.8333,"angle":-0.17,"curve":"stepped"},{"time":12.6666,"angle":-0.17,"curve":"stepped"},{"time":13.6666,"angle":-0.17}],"translate":[{"time":0,"x":0.01,"y":-2.09},{"time":0.5,"x":0,"y":-0.09},{"time":1,"x":0.01,"y":-2.09},{"time":1.5,"x":0,"y":-0.09},{"time":2,"x":0.01,"y":-2.09},{"time":2.5,"x":0,"y":-0.09},{"time":3,"x":0.01,"y":-2.09},{"time":3.5,"x":0,"y":-0.09},{"time":4,"x":0.01,"y":-2.09},{"time":5.5,"x":0,"y":-0.09,"curve":"stepped"},{"time":6,"x":0,"y":-0.09},{"time":6.1666,"x":0.01,"y":-2.09},{"time":6.5,"x":0,"y":-0.09},{"time":7,"x":0.01,"y":-2.09},{"time":7.5,"x":0,"y":-0.09},{"time":8,"x":0.01,"y":-2.09},{"time":8.5,"x":0,"y":-0.09},{"time":9,"x":0.01,"y":-2.09},{"time":9.5,"x":0,"y":-0.09},{"time":9.6666,"x":0.01,"y":-2.09,"curve":"stepped"},{"time":10,"x":0.01,"y":-2.09,"curve":"stepped"},{"time":10.8333,"x":0.01,"y":-2.09,"curve":"stepped"},{"time":11.2,"x":0.01,"y":-2.09,"curve":"stepped"},{"time":11.8333,"x":0.01,"y":-2.09,"curve":"stepped"},{"time":12.6666,"x":0.01,"y":-2.09,"curve":"stepped"},{"time":13.6666,"x":0.01,"y":-2.09}]},"leftLowerLeg":{"rotate":[{"time":0,"angle":-0.17,"curve":"stepped"},{"time":1,"angle":-0.17},{"time":2,"angle":-8.9},{"time":3,"angle":-0.17,"curve":"stepped"},{"time":4,"angle":-0.17,"curve":"stepped"},{"time":6,"angle":-0.17,"curve":"stepped"},{"time":6.1666,"angle":-0.17,"curve":"stepped"},{"time":7,"angle":-0.17,"curve":"stepped"},{"time":8,"angle":-0.17,"curve":"stepped"},{"time":9,"angle":-0.17,"curve":"stepped"},{"time":9.6666,"angle":-0.17,"curve":"stepped"},{"time":10,"angle":-0.17,"curve":"stepped"},{"time":10.8333,"angle":-0.17,"curve":"stepped"},{"time":11.2,"angle":-0.17,"curve":"stepped"},{"time":11.8333,"angle":-0.17,"curve":"stepped"},{"time":12.6666,"angle":-0.17,"curve":"stepped"},{"time":13.6666,"angle":-0.17}]},"leftUpperArm":{"rotate":[{"time":0,"angle":-0.17,"curve":"stepped"},{"time":1,"angle":-0.17,"curve":"stepped"},{"time":2,"angle":-0.17,"curve":"stepped"},{"time":3,"angle":-0.17,"curve":"stepped"},{"time":4,"angle":-0.17},{"time":5.5,"angle":312.25},{"time":6,"angle":-0.17,"curve":"stepped"},{"time":6.1666,"angle":-0.17,"curve":"stepped"},{"time":7,"angle":-0.17,"curve":"stepped"},{"time":8,"angle":-0.17,"curve":"stepped"},{"time":9,"angle":-0.17,"curve":"stepped"},{"time":9.6666,"angle":-0.17,"curve":"stepped"},{"time":10,"angle":-0.17,"curve":"stepped"},{"time":10.8333,"angle":-0.17,"curve":"stepped"},{"time":11.2,"angle":-0.17,"curve":"stepped"},{"time":11.8333,"angle":-0.17,"curve":"stepped"},{"time":12.6666,"angle":-0.17,"curve":"stepped"},{"time":13.6666,"angle":-0.17}]},"neck":{"rotate":[{"time":0,"angle":-0.17,"curve":"stepped"},{"time":1,"angle":-0.17,"curve":"stepped"},{"time":2,"angle":-0.17,"curve":"stepped"},{"time":3,"angle":-0.17,"curve":"stepped"},{"time":4,"angle":-0.17,"curve":"stepped"},{"time":6,"angle":-0.17,"curve":"stepped"},{"time":6.1666,"angle":-0.17,"curve":"stepped"},{"time":7,"angle":-0.17,"curve":"stepped"},{"time":8,"angle":-0.17,"curve":"stepped"},{"time":9,"angle":-0.17,"curve":"stepped"},{"time":9.6666,"angle":-0.17,"curve":"stepped"},{"time":10,"angle":-0.17,"curve":"stepped"},{"time":10.8333,"angle":-0.17,"curve":"stepped"},{"time":11.2,"angle":-0.17,"curve":"stepped"},{"time":11.8333,"angle":-0.17,"curve":"stepped"},{"time":12.6666,"angle":-0.17,"curve":"stepped"},{"time":13.6666,"angle":-0.17}]},"rightLowerLeg":{"rotate":[{"time":0,"angle":-0.17,"curve":"stepped"},{"time":1,"angle":-0.17},{"time":2,"angle":-37.12},{"time":3,"angle":-0.17,"curve":"stepped"},{"time":4,"angle":-0.17},{"time":4.1666,"angle":-22.83},{"time":6,"angle":-0.17,"curve":"stepped"},{"time":6.1666,"angle":-0.17,"curve":"stepped"},{"time":7,"angle":-0.17,"curve":"stepped"},{"time":8,"angle":-0.17,"curve":"stepped"},{"time":9,"angle":-0.17,"curve":"stepped"},{"time":9.6666,"angle":-0.17},{"time":10,"angle":-125.72},{"time":10.3333,"angle":-130.22},{"time":10.8333,"angle":-125.72},{"time":11.2,"angle":-0.17,"curve":"stepped"},{"time":11.8333,"angle":-0.17,"curve":"stepped"},{"time":12.6666,"angle":-0.17,"curve":"stepped"},{"time":13.6666,"angle":-0.17}]},"rightUpperArm":{"rotate":[{"time":0,"angle":-0.17,"curve":"stepped"},{"time":1,"angle":-0.17,"curve":"stepped"},{"time":2,"angle":-0.17,"curve":"stepped"},{"time":3,"angle":-0.17},{"time":3.6666,"angle":5.94},{"time":4,"angle":312.21},{"time":5.5,"angle":311.49},{"time":6,"angle":-0.17,"curve":"stepped"},{"time":6.1666,"angle":-0.17,"curve":"stepped"},{"time":7,"angle":-0.17,"curve":"stepped"},{"time":8,"angle":-0.17,"curve":"stepped"},{"time":9,"angle":-0.17,"curve":"stepped"},{"time":9.6666,"angle":-0.17},{"time":10,"angle":29.82,"curve":"stepped"},{"time":10.8333,"angle":29.82},{"time":11.2,"angle":-0.17,"curve":"stepped"},{"time":11.8333,"angle":-0.17,"curve":"stepped"},{"time":12.6666,"angle":-0.17,"curve":"stepped"},{"time":13.6666,"angle":-0.17}]},"head":{"rotate":[{"time":0,"angle":-0.17,"curve":"stepped"},{"time":1,"angle":-0.17,"curve":"stepped"},{"time":2,"angle":-0.17,"curve":"stepped"},{"time":3,"angle":-0.17},{"time":3.8333,"angle":5.48},{"time":4,"angle":18.22},{"time":6,"angle":-0.17,"curve":"stepped"},{"time":6.1666,"angle":-0.17,"curve":"stepped"},{"time":7,"angle":-0.17,"curve":"stepped"},{"time":8,"angle":-0.17,"curve":"stepped"},{"time":9,"angle":-0.17,"curve":"stepped"},{"time":9.6666,"angle":-0.17,"curve":"stepped"},{"time":10,"angle":-0.17,"curve":"stepped"},{"time":10.8333,"angle":-0.17,"curve":"stepped"},{"time":11.2,"angle":-0.17,"curve":"stepped"},{"time":11.8333,"angle":-0.17,"curve":"stepped"},{"time":12.6666,"angle":-0.17,"curve":"stepped"},{"time":13.6666,"angle":-0.17}]},"leftFoot":{"rotate":[{"time":0,"angle":-0.17,"curve":"stepped"},{"time":1,"angle":-0.17,"curve":"stepped"},{"time":2,"angle":-0.17,"curve":"stepped"},{"time":3,"angle":-0.17,"curve":"stepped"},{"time":4,"angle":-0.17,"curve":"stepped"},{"time":6,"angle":-0.17,"curve":"stepped"},{"time":6.1666,"angle":-0.17,"curve":"stepped"},{"time":7,"angle":-0.17,"curve":"stepped"},{"time":8,"angle":-0.17,"curve":"stepped"},{"time":9,"angle":-0.17,"curve":"stepped"},{"time":9.6666,"angle":-0.17,"curve":"stepped"},{"time":10,"angle":-0.17,"curve":"stepped"},{"time":10.8333,"angle":-0.17,"curve":"stepped"},{"time":11.2,"angle":-0.17,"curve":"stepped"},{"time":11.8333,"angle":-0.17,"curve":"stepped"},{"time":12.6666,"angle":-0.17,"curve":"stepped"},{"time":13.6666,"angle":-0.17}]},"leftLowerArm":{"rotate":[{"time":0,"angle":-0.17,"curve":"stepped"},{"time":1,"angle":-0.17,"curve":"stepped"},{"time":2,"angle":-0.17,"curve":"stepped"},{"time":3,"angle":-0.17,"curve":"stepped"},{"time":4,"angle":-0.17},{"time":5.5,"angle":75.71},{"time":6,"angle":-0.17,"curve":"stepped"},{"time":6.1666,"angle":-0.17,"curve":"stepped"},{"time":7,"angle":-0.17,"curve":"stepped"},{"time":8,"angle":-0.17,"curve":"stepped"},{"time":9,"angle":-0.17,"curve":"stepped"},{"time":9.6666,"angle":-0.17,"curve":"stepped"},{"time":10,"angle":-0.17,"curve":"stepped"},{"time":10.8333,"angle":-0.17,"curve":"stepped"},{"time":11.2,"angle":-0.17,"curve":"stepped"},{"time":11.8333,"angle":-0.17,"curve":"stepped"},{"time":12.6666,"angle":-0.17,"curve":"stepped"},{"time":13.6666,"angle":-0.17}]},"rightFoot":{"rotate":[{"time":0,"angle":-0.17,"curve":"stepped"},{"time":1,"angle":-0.17,"curve":"stepped"},{"time":2,"angle":-0.17,"curve":"stepped"},{"time":3,"angle":-0.17,"curve":"stepped"},{"time":4,"angle":-0.17,"curve":"stepped"},{"time":6,"angle":-0.17,"curve":"stepped"},{"time":6.1666,"angle":-0.17,"curve":"stepped"},{"time":7,"angle":-0.17,"curve":"stepped"},{"time":8,"angle":-0.17,"curve":"stepped"},{"time":9,"angle":-0.17,"curve":"stepped"},{"time":9.6666,"angle":-0.17,"curve":"stepped"},{"time":10,"angle":-0.17,"curve":"stepped"},{"time":10.8333,"angle":-0.17,"curve":"stepped"},{"time":11.2,"angle":-0.17,"curve":"stepped"},{"time":11.8333,"angle":-0.17,"curve":"stepped"},{"time":12.6666,"angle":-0.17,"curve":"stepped"},{"time":13.6666,"angle":-0.17}]},"rightLowerArm":{"rotate":[{"time":0,"angle":-0.17,"curve":"stepped"},{"time":1,"angle":-0.17,"curve":"stepped"},{"time":2,"angle":-0.17,"curve":"stepped"},{"time":3,"angle":-0.17},{"time":4,"angle":70.59},{"time":5.5,"angle":87.37},{"time":6,"angle":-0.17,"curve":"stepped"},{"time":6.1666,"angle":-0.17,"curve":"stepped"},{"time":7,"angle":-0.17,"curve":"stepped"},{"time":8,"angle":-0.17,"curve":"stepped"},{"time":9,"angle":-0.17,"curve":"stepped"},{"time":9.6666,"angle":-0.17},{"time":10,"angle":48.66,"curve":"stepped"},{"time":10.8333,"angle":48.66},{"time":11.2,"angle":-0.17,"curve":"stepped"},{"time":11.8333,"angle":-0.17,"curve":"stepped"},{"time":12.6666,"angle":-0.17,"curve":"stepped"},{"time":13.6666,"angle":-0.17}]},"leftHand":{"rotate":[{"time":0,"angle":-0.17,"curve":"stepped"},{"time":1,"angle":-0.17,"curve":"stepped"},{"time":2,"angle":-0.17,"curve":"stepped"},{"time":3,"angle":-0.17,"curve":"stepped"},{"time":4,"angle":-0.17,"curve":"stepped"},{"time":6,"angle":-0.17,"curve":"stepped"},{"time":6.1666,"angle":-0.17,"curve":"stepped"},{"time":7,"angle":-0.17,"curve":"stepped"},{"time":8,"angle":-0.17,"curve":"stepped"},{"time":9,"angle":-0.17,"curve":"stepped"},{"time":9.6666,"angle":-0.17,"curve":"stepped"},{"time":10,"angle":-0.17,"curve":"stepped"},{"time":10.8333,"angle":-0.17,"curve":"stepped"},{"time":11.2,"angle":-0.17,"curve":"stepped"},{"time":11.8333,"angle":-0.17,"curve":"stepped"},{"time":12.6666,"angle":-0.17,"curve":"stepped"},{"time":13.6666,"angle":-0.17}]},"rightHand":{"rotate":[{"time":0,"angle":-0.17,"curve":"stepped"},{"time":1,"angle":-0.17,"curve":"stepped"},{"time":2,"angle":-0.17,"curve":"stepped"},{"time":3,"angle":-0.17,"curve":"stepped"},{"time":4,"angle":-0.17,"curve":"stepped"},{"time":6,"angle":-0.17,"curve":"stepped"},{"time":6.1666,"angle":-0.17,"curve":"stepped"},{"time":7,"angle":-0.17,"curve":"stepped"},{"time":8,"angle":-0.17,"curve":"stepped"},{"time":9,"angle":-0.17,"curve":"stepped"},{"time":9.6666,"angle":-0.17,"curve":"stepped"},{"time":10,"angle":-0.17,"curve":"stepped"},{"time":10.8333,"angle":-0.17,"curve":"stepped"},{"time":11.2,"angle":-0.17,"curve":"stepped"},{"time":11.8333,"angle":-0.17,"curve":"stepped"},{"time":12.6666,"angle":-0.17,"curve":"stepped"},{"time":13.6666,"angle":-0.17}]}},"slots":{"left hooked arm":{"attachment":[{"time":0,"name":null},{"time":1,"name":null},{"time":2,"name":null},{"time":3,"name":null},{"time":4,"name":null},{"time":6,"name":null},{"time":6.1666,"name":null},{"time":7,"name":null},{"time":8,"name":null},{"time":9,"name":null},{"time":9.6666,"name":null},{"time":10,"name":null},{"time":10.8333,"name":null},{"time":11.2,"name":null},{"time":11.8333,"name":null},{"time":12.6666,"name":null},{"time":13.6666,"name":null}]},"right hooked arm":{"attachment":[{"time":0,"name":null},{"time":1,"name":null},{"time":2,"name":null},{"time":3,"name":null},{"time":4,"name":null},{"time":6,"name":null},{"time":6.1666,"name":null},{"time":7,"name":null},{"time":8,"name":null},{"time":9,"name":null},{"time":9.6666,"name":null},{"time":10,"name":null},{"time":10.8333,"name":null},{"time":11.2,"name":null},{"time":11.8333,"name":null},{"time":12.6666,"name":null},{"time":13.6666,"name":null}]},"right open hand":{"attachment":[{"time":0,"name":null},{"time":1,"name":null},{"time":2,"name":null},{"time":3,"name":null},{"time":4,"name":null},{"time":6,"name":null},{"time":6.1666,"name":null},{"time":7,"name":null},{"time":8,"name":null},{"time":9,"name":null},{"time":9.6666,"name":null},{"time":10,"name":null},{"time":10.8333,"name":null},{"time":11.2,"name":null},{"time":11.8333,"name":null},{"time":12.6666,"name":null},{"time":13.6666,"name":null}]}}},"jogging":{"bones":{"leftUpperLeg":{"rotate":[{"time":0,"angle":48.92},{"time":0.1,"angle":47.16},{"time":0.2,"angle":28.35},{"time":0.3,"angle":7.33},{"time":0.5,"angle":-16.92},{"time":0.6666,"angle":-12.02},{"time":0.8333,"angle":17.59},{"time":0.9,"angle":36.71},{"time":1,"angle":48.92}],"translate":[{"time":0.6666,"x":0,"y":1}]},"rightUpperLeg":{"rotate":[{"time":0,"angle":-20.86},{"time":0.1,"angle":-9.6},{"time":0.2,"angle":1.27},{"time":0.3,"angle":19.02},{"time":0.5,"angle":45.64},{"time":0.6666,"angle":34.78},{"time":1,"angle":-20.86}]},"spine":{"rotate":[{"time":0,"angle":-6.75},{"time":0.1,"angle":-8.41},{"time":0.2,"angle":-7.36},{"time":0.3,"angle":-7.4},{"time":0.6666,"angle":-10.25},{"time":0.8333,"angle":-8.53},{"time":0.9,"angle":-6.55},{"time":1,"angle":-6.75}]},"leftLowerLeg":{"rotate":[{"time":0,"angle":-70.86},{"time":0.1,"angle":-40.8},{"time":0.2,"angle":-29.9},{"time":0.3,"angle":-21.17},{"time":0.5,"angle":-22.84},{"time":0.6666,"angle":-53.87},{"time":0.8333,"angle":-89.52},{"time":0.9,"angle":-89.03},{"time":1,"angle":-70.86}]},"leftUpperArm":{"rotate":[{"time":0,"angle":326.78},{"time":0.1,"angle":320.06},{"time":0.2,"angle":328.43},{"time":0.3,"angle":353.15},{"time":0.5,"angle":6.16},{"time":0.6666,"angle":-0.13},{"time":0.8333,"angle":338.18},{"time":1,"angle":326.78}]},"rightLowerLeg":{"rotate":[{"time":0,"angle":-30.03},{"time":0.1,"angle":-56.85},{"time":0.2,"angle":-74.93},{"time":0.3,"angle":-114.69},{"time":0.5,"angle":-70.46},{"time":0.6666,"angle":-22.25},{"time":0.9,"angle":-20.86},{"time":1,"angle":-30.03}]},"rightUpperArm":{"rotate":[{"time":0,"angle":17.71},{"time":0.2,"angle":11.74},{"time":0.3,"angle":348.43},{"time":0.5,"angle":326.44},{"time":0.6666,"angle":319.61},{"time":0.8333,"angle":352.49},{"time":0.9,"angle":15.23},{"time":1,"angle":17.71}]},"head":{"rotate":[{"time":0,"angle":-0.46,"curve":"stepped"},{"time":0.1,"angle":2.93},{"time":0.2,"angle":3.84},{"time":0.3,"angle":5.64},{"time":0.8333,"angle":5.06},{"time":1,"angle":-0.46}]},"leftLowerArm":{"rotate":[{"time":0,"angle":106.71},{"time":0.1,"angle":91.76},{"time":0.2,"angle":77.44},{"time":0.5,"angle":113.51},{"time":0.6666,"angle":123.43},{"time":0.8333,"angle":78.24},{"time":1,"angle":106.71}]},"rightLowerArm":{"rotate":[{"time":0,"angle":95.86},{"time":0.1,"angle":76.75},{"time":0.2,"angle":44.65},{"time":0.3,"angle":44.05},{"time":0.5,"angle":100.57},{"time":0.8333,"angle":80.15},{"time":0.9,"angle":77.81},{"time":0.9666,"angle":94.8},{"time":1,"angle":95.86}]},"rightFoot":{"rotate":[{"time":0,"angle":-23.86},{"time":0.1,"angle":-20.24},{"time":0.2,"angle":-26.51},{"time":0.3,"angle":-3.82},{"time":0.5,"angle":0.11},{"time":0.6666,"angle":3.46},{"time":0.9,"angle":19.01},{"time":1,"angle":-23.86}]},"leftFoot":{"rotate":[{"time":0,"angle":4.07},{"time":0.3,"angle":11.32},{"time":0.6666,"angle":-6.19},{"time":1,"angle":4.07}]},"rightHand":{"rotate":[{"time":0,"angle":2.77,"curve":"stepped"},{"time":1,"angle":2.77}]},"leftHand":{"rotate":[{"time":0,"angle":3.77},{"time":0.5,"angle":19.45},{"time":1,"angle":3.77}]},"neck":{"rotate":[{"time":0,"angle":-3.41,"curve":"stepped"},{"time":1,"angle":-3.41}]},"root":{"translate":[{"time":0,"x":0,"y":5.38},{"time":0.3,"x":0,"y":-8.61},{"time":0.5,"x":0,"y":5.38},{"time":0.8333,"x":0,"y":-6.46},{"time":1,"x":0,"y":5.38}]}},"slots":{"left hooked arm":{"attachment":[{"time":0,"name":null},{"time":1,"name":null}]},"right hooked arm":{"attachment":[{"time":0,"name":null},{"time":1,"name":null}]},"right open hand":{"attachment":[{"time":0,"name":null},{"time":1,"name":null}]}}},"lieDown":{"bones":{"spine":{"rotate":[{"time":0,"angle":-2.47},{"time":0.1666,"angle":-9.78},{"time":0.6666,"angle":-61.1},{"time":0.8333,"angle":-66.39},{"time":1,"angle":-80.4},{"time":1.3333,"angle":-95.74}]},"rightUpperArm":{"rotate":[{"time":0,"angle":10.96},{"time":0.6666,"angle":61.51},{"time":1,"angle":39.96},{"time":1.1666,"angle":83.34},{"time":1.3333,"angle":100.27}]},"leftUpperArm":{"rotate":[{"time":0,"angle":8.53},{"time":0.8333,"angle":69.51},{"time":1.1666,"angle":353.74},{"time":1.3333,"angle":309.4}]},"head":{"rotate":[{"time":0,"angle":-7.44},{"time":1.3333,"angle":29.98}]},"rightUpperLeg":{"rotate":[{"time":0,"angle":-0.86},{"time":0.1666,"angle":-21.5},{"time":0.3333,"angle":-35.49},{"time":0.5,"angle":-13.75},{"time":0.6666,"angle":-31.36},{"time":1,"angle":-45.09},{"time":1.1666,"angle":-68.94},{"time":1.3333,"angle":-92.32}]},"leftUpperLeg":{"rotate":[{"time":0,"angle":-0.36},{"time":0.1666,"angle":6.06},{"time":0.3333,"angle":29.29},{"time":0.5,"angle":73.01},{"time":0.6666,"angle":28.51},{"time":0.8333,"angle":-4.06},{"time":1,"angle":-39.08},{"time":1.1666,"angle":-67.38},{"time":1.3333,"angle":-90.76}]},"leftLowerLeg":{"rotate":[{"time":0.1666,"angle":-7.02},{"time":0.3333,"angle":-30.48},{"time":0.5,"angle":-72.09},{"time":0.6666,"angle":-117.14},{"time":0.8333,"angle":-94.18},{"time":1,"angle":-49.83},{"time":1.3333,"angle":-8.94}]},"hip":{"translate":[{"time":0,"x":0,"y":1.32},{"time":0.1666,"x":0,"y":-2.65},{"time":0.3333,"x":0,"y":-18.59},{"time":0.5,"x":0,"y":-92.95},{"time":0.6666,"x":0,"y":-138.11},{"time":1.1666,"x":0,"y":-193.88},{"time":1.3333,"x":0,"y":-239.03}]},"rightLowerLeg":{"rotate":[{"time":0,"angle":-0.42},{"time":0.3333,"angle":-19.61},{"time":0.5,"angle":-71.6},{"time":0.6666,"angle":-66.43},{"time":1,"angle":-42.86},{"time":1.3333,"angle":-1.97}]},"leftLowerArm":{"rotate":[{"time":0,"angle":1.46},{"time":0.8333,"angle":25.01},{"time":1,"angle":58.38},{"time":1.1666,"angle":102.81}]},"rightLowerArm":{"rotate":[{"time":0,"angle":1.56},{"time":1,"angle":35.25},{"time":1.3333,"angle":6.29}]}},"slots":{"left hooked arm":{"attachment":[{"time":0,"name":null}]},"right closed hand":{"attachment":[{"time":1.2333,"name":null}]},"right hooked arm":{"attachment":[{"time":0,"name":null}]},"right open hand":{"attachment":[{"time":0,"name":null},{"time":1.2333,"name":"right open hand"}]}}},"pullUp":{"bones":{"leftUpperArm":{"rotate":[{"time":0,"angle":322.08},{"time":0.1666,"angle":334.83},{"time":0.3333,"angle":355.16},{"time":0.5,"angle":18.04},{"time":0.6666,"angle":32.15},{"time":0.8333,"angle":64.16},{"time":1,"angle":52.02},{"time":1.1666,"angle":55.37},{"time":1.5,"angle":33.48},{"time":1.6666,"angle":348.3},{"time":1.8333,"angle":326.42},{"time":2,"angle":333.48},{"time":2.3333,"angle":18.77},{"time":2.5,"angle":1.57}]},"rightUpperArm":{"rotate":[{"time":0,"angle":100.27},{"time":0.3333,"angle":86.07},{"time":0.8333,"angle":74.5},{"time":1,"angle":62.35},{"time":1.1666,"angle":65.71},{"time":1.5,"angle":316.85},{"time":2.3333,"angle":9.09},{"time":2.5,"angle":354.56}]},"rightLowerLeg":{"rotate":[{"time":0,"angle":-1.97},{"time":0.5,"angle":-28.23},{"time":0.6666,"angle":-70.46},{"time":0.8333,"angle":-110.52},{"time":1.5,"angle":-47.43},{"time":2.1666,"angle":-110.25},{"time":2.3333,"angle":-70.61},{"time":2.5,"angle":-14.28}]},"rightUpperLeg":{"rotate":[{"time":0,"angle":-92.32},{"time":0.5,"angle":-64.57},{"time":0.6666,"angle":-26.62},{"time":0.8333,"angle":15.9},{"time":1.3333,"angle":99.72},{"time":1.5,"angle":110.96},{"time":1.6666,"angle":123.02},{"time":2,"angle":91.37},{"time":2.1666,"angle":58.66},{"time":2.3333,"angle":9.77}]},"hip":{"translate":[{"time":0,"x":0,"y":-239.03},{"time":0.5,"x":0,"y":-178.99},{"time":0.6666,"x":-11.25,"y":-141.46},{"time":1.3333,"x":-150.11,"y":-141.46},{"time":1.6666,"x":-236.42,"y":-239.03},{"time":2.3333,"x":-18.38,"y":-30.75},{"time":2.5,"x":-11.82,"y":-0.73}]},"spine":{"rotate":[{"time":0,"angle":-95.74},{"time":0.1666,"angle":-84.51},{"time":0.3333,"angle":-52.07},{"time":0.8333,"angle":-37.35},{"time":1,"angle":-4.55},{"time":1.1666,"angle":18.12},{"time":1.3333,"angle":33.17},{"time":1.5,"angle":44.01},{"time":2,"angle":5.21},{"time":2.1666,"angle":22.09},{"time":2.3333,"angle":3.91}]},"leftLowerLeg":{"rotate":[{"time":0,"angle":-8.94},{"time":0.5,"angle":-28.72},{"time":0.6666,"angle":-58.91},{"time":0.8333,"angle":-89.79},{"time":1,"angle":-117.9},{"time":1.4,"angle":-94.87},{"time":1.5,"angle":-48.65},{"time":2.1666,"angle":-90},{"time":2.3333,"angle":-46.57},{"time":2.5,"angle":-5.54}]},"head":{"rotate":[{"time":0,"angle":29.98},{"time":2,"angle":-19.67},{"time":2.5,"angle":-1.87}]},"rightLowerArm":{"rotate":[{"time":0,"angle":6.29},{"time":1.1666,"angle":-2.21},{"time":1.5,"angle":29.61},{"time":1.6666,"angle":76.5},{"time":1.8333,"angle":16.48},{"time":2,"angle":33.39},{"time":2.5,"angle":10.74}]},"leftUpperLeg":{"rotate":[{"time":0,"angle":-90.76},{"time":0.5,"angle":-63.79},{"time":0.6666,"angle":-28.57},{"time":0.8333,"angle":-12.67},{"time":1,"angle":21.02},{"time":1.0666,"angle":61.81},{"time":1.1666,"angle":93.73},{"time":1.6666,"angle":120.17},{"time":1.8333,"angle":111.24},{"time":2,"angle":86.89},{"time":2.1666,"angle":61.96},{"time":2.3333,"angle":34.49},{"time":2.5,"angle":4.22}]},"leftLowerArm":{"rotate":[{"time":0,"angle":103.95},{"time":0.3333,"angle":70.77},{"time":0.5,"angle":52.91},{"time":0.6666,"angle":26.7},{"time":1.1666,"angle":6.79},{"time":1.6666,"angle":48.76},{"time":2,"angle":17.4}]}},"slots":{"left hooked arm":{"attachment":[{"time":0,"name":null}]},"right hooked arm":{"attachment":[{"time":0,"name":null}]},"right open hand":{"attachment":[{"time":0,"name":null}]}}},"pushing":{"bones":{"rightUpperArm":{"rotate":[{"time":0,"angle":98.14,"curve":"stepped"},{"time":1.5,"angle":98.14}]},"leftUpperArm":{"rotate":[{"time":0,"angle":93.93,"curve":"stepped"},{"time":1.5,"angle":93.93}]},"rightLowerArm":{"rotate":[{"time":0,"angle":35.88,"curve":"stepped"},{"time":1.5,"angle":35.88}]},"leftUpperLeg":{"rotate":[{"time":0,"angle":57.63},{"time":0.6666,"angle":-10.3},{"time":1.5,"angle":57.63}]},"rightUpperLeg":{"rotate":[{"time":0,"angle":-23.93},{"time":0.6666,"angle":56.28},{"time":1.5,"angle":-23.93}]},"leftLowerLeg":{"rotate":[{"time":0,"angle":-74.31},{"time":0.3333,"angle":-53.68},{"time":0.6666,"angle":-53.33},{"time":1,"angle":-74.03},{"time":1.5,"angle":-74.31}]},"rightLowerLeg":{"rotate":[{"time":0,"angle":-38.03},{"time":0.3333,"angle":-75.1},{"time":0.6666,"angle":-75.85},{"time":1.5,"angle":-38.03}]},"leftLowerArm":{"rotate":[{"time":0,"angle":44.86,"curve":"stepped"},{"time":1.5,"angle":44.86}]},"hip":{"translate":[{"time":0,"x":-195.07,"y":-67.8},{"time":0.3333,"x":-195.07,"y":-36.66},{"time":0.6666,"x":-195.07,"y":-68.51},{"time":1,"x":-195.07,"y":-37.08},{"time":1.5,"x":-195.07,"y":-67.8}]},"leftFoot":{"rotate":[{"time":0,"angle":17.41},{"time":0.6666,"angle":44.3},{"time":1.5,"angle":17.41}]},"rightFoot":{"rotate":[{"time":0,"angle":37.9},{"time":0.6666,"angle":15.1},{"time":1.5,"angle":37.9}]},"spine":{"rotate":[{"time":0,"angle":-42.24,"curve":"stepped"},{"time":1.5,"angle":-42.24}]},"neck":{"rotate":[{"time":0,"angle":-1.06,"curve":"stepped"},{"time":1.5,"angle":-1.06}]},"head":{"rotate":[{"time":0,"angle":-23.99},{"time":0.3333,"angle":0.37},{"time":0.6666,"angle":8},{"time":1,"angle":-26.9},{"time":1.5,"angle":-23.99}]}},"slots":{"left hooked arm":{"attachment":[{"time":0,"name":null},{"time":1.5,"name":null}]},"right hooked arm":{"attachment":[{"time":0,"name":null},{"time":1.5,"name":null}]},"right open hand":{"attachment":[{"time":0,"name":null},{"time":1.5,"name":null}]}}},"runJumping":{"bones":{"leftUpperArm":{"rotate":[{"time":0,"angle":85.51},{"time":0.1666,"angle":72.49},{"time":0.6666,"angle":311.13}]},"rightUpperArm":{"rotate":[{"time":0,"angle":95.96},{"time":0.1666,"angle":68.7},{"time":0.6666,"angle":322.66}]},"root":{"translate":[{"time":0,"x":0,"y":63.74}]},"leftUpperLeg":{"rotate":[{"time":0,"angle":-45.22},{"time":0.1666,"angle":-24.41},{"time":0.3333,"angle":11.26},{"time":0.5,"angle":60},{"time":0.6666,"angle":65.07}]},"leftLowerLeg":{"rotate":[{"time":0,"angle":-20.24},{"time":0.1666,"angle":-65.37},{"time":0.5,"angle":-113.3},{"time":0.6666,"angle":-49.7}]},"leftFoot":{"rotate":[{"time":0,"angle":4.82},{"time":0.1666,"angle":-3.9}]},"rightUpperLeg":{"rotate":[{"time":0,"angle":68.92},{"time":0.1666,"angle":62.67},{"time":0.3333,"angle":41.38},{"time":0.5,"angle":59.96},{"time":0.6666,"angle":68.28}]},"rightLowerLeg":{"rotate":[{"time":0,"angle":-120.04},{"time":0.3333,"angle":-93.46},{"time":0.6666,"angle":-34.98}]},"spine":{"rotate":[{"time":0,"angle":-3.76},{"time":0.1666,"angle":-13.57},{"time":0.3333,"angle":-15.29}]},"rightLowerArm":{"rotate":[{"time":0,"angle":50.04},{"time":0.1666,"angle":77.62}]},"leftLowerArm":{"rotate":[{"time":0,"angle":40.23},{"time":0.1666,"angle":69.08}]},"head":{"rotate":[{"time":0,"angle":15.75},{"time":0.5,"angle":7.27}]}},"slots":{"left hooked arm":{"attachment":[{"time":0,"name":null}]},"right hooked arm":{"attachment":[{"time":0,"name":null}]},"right open hand":{"attachment":[{"time":0,"name":null}]}}},"running":{"bones":{"leftUpperLeg":{"rotate":[{"time":0,"angle":65.37},{"time":0.1,"angle":47.16},{"time":0.2,"angle":28.35},{"time":0.3,"angle":7.33},{"time":0.4,"angle":-4.67},{"time":0.5,"angle":-33.59},{"time":0.6,"angle":-22.64},{"time":0.7,"angle":-12.02},{"time":0.8,"angle":17.59},{"time":0.9,"angle":36.71},{"time":1,"angle":65.37}],"translate":[{"time":0.7,"x":0,"y":1}]},"rightUpperLeg":{"rotate":[{"time":0,"angle":-33.68},{"time":0.1,"angle":-9.6},{"time":0.2,"angle":1.27},{"time":0.3,"angle":19.02},{"time":0.4,"angle":48.27},{"time":0.5,"angle":63.75},{"time":0.6,"angle":48.27},{"time":0.7,"angle":34.78},{"time":1,"angle":-33.68}]},"spine":{"rotate":[{"time":0,"angle":-11.53},{"time":0.5,"angle":-13.13},{"time":1,"angle":-11.53}]},"leftLowerLeg":{"rotate":[{"time":0,"angle":-70.86},{"time":0.1,"angle":-40.8},{"time":0.2,"angle":-29.9},{"time":0.3,"angle":-21.17},{"time":0.4,"angle":-24.86},{"time":0.5,"angle":-22.84},{"time":0.6,"angle":-61.21},{"time":0.7,"angle":-99.97},{"time":0.8,"angle":-117.86},{"time":0.9,"angle":-89.03},{"time":1,"angle":-70.86}]},"leftUpperArm":{"rotate":[{"time":0,"angle":299.28},{"time":0.1,"angle":320.06},{"time":0.2,"angle":328.43},{"time":0.3,"angle":353.15},{"time":0.4,"angle":7.64},{"time":0.5,"angle":26.69},{"time":0.6,"angle":37.59},{"time":0.7,"angle":-0.13},{"time":0.8,"angle":338.18},{"time":1,"angle":299.28}]},"rightLowerLeg":{"rotate":[{"time":0,"angle":-30.03},{"time":0.1,"angle":-88.61},{"time":0.2,"angle":-104.64},{"time":0.3,"angle":-114.69},{"time":0.4,"angle":-108.91},{"time":0.5,"angle":-70.46},{"time":0.6,"angle":-38.48},{"time":0.7,"angle":-22.25},{"time":0.9,"angle":-20.86},{"time":1,"angle":-30.03}]},"rightUpperArm":{"rotate":[{"time":0,"angle":46.51},{"time":0.1,"angle":21.2},{"time":0.2,"angle":11.74},{"time":0.3,"angle":348.43},{"time":0.4,"angle":323.07},{"time":0.5,"angle":293.85},{"time":0.6,"angle":280.46},{"time":0.7,"angle":302.93},{"time":0.8,"angle":352.49},{"time":0.9,"angle":15.23},{"time":1,"angle":46.51}]},"head":{"rotate":[{"time":0,"angle":14.22,"curve":"stepped"},{"time":0.5,"angle":13.74},{"time":1,"angle":14.22}]},"leftLowerArm":{"rotate":[{"time":0,"angle":106.71},{"time":0.1,"angle":91.76},{"time":0.2,"angle":77.44},{"time":0.5,"angle":113.51},{"time":0.6,"angle":119.71},{"time":0.7,"angle":111.83},{"time":0.8,"angle":78.24},{"time":1,"angle":106.71}]},"rightLowerArm":{"rotate":[{"time":0,"angle":95.86},{"time":0.1,"angle":76.75},{"time":0.2,"angle":44.65},{"time":0.3,"angle":44.05},{"time":0.5,"angle":84.31},{"time":0.8,"angle":80.15},{"time":0.9,"angle":77.81},{"time":1,"angle":95.86}]},"rightFoot":{"rotate":[{"time":0,"angle":-23.86},{"time":0.1,"angle":-20.24},{"time":0.2,"angle":-26.51},{"time":0.3,"angle":-3.82},{"time":0.5,"angle":0.11},{"time":0.6,"angle":-8.64},{"time":0.7,"angle":3.46},{"time":0.9,"angle":19.01},{"time":1,"angle":-23.86}]},"leftFoot":{"rotate":[{"time":0,"angle":4.07},{"time":0.3,"angle":11.32},{"time":0.7,"angle":-6.19},{"time":1,"angle":4.07}]},"rightHand":{"rotate":[{"time":0,"angle":2.77,"curve":"stepped"},{"time":1,"angle":2.77}]},"leftHand":{"rotate":[{"time":0,"angle":3.77},{"time":0.5,"angle":19.45},{"time":1,"angle":3.77}]},"neck":{"rotate":[{"time":0,"angle":-3.41,"curve":"stepped"},{"time":1,"angle":-3.41}]},"root":{"translate":[{"time":0,"x":0,"y":5.38},{"time":0.3,"x":0,"y":-8.61},{"time":0.5,"x":0,"y":5.38},{"time":0.8333,"x":0,"y":-6.46},{"time":1,"x":0,"y":5.38}]}},"slots":{"left hooked arm":{"attachment":[{"time":0,"name":null},{"time":1,"name":null}]},"right hooked arm":{"attachment":[{"time":0,"name":null},{"time":1,"name":null}]},"right open hand":{"attachment":[{"time":0,"name":null},{"time":1,"name":null}]}}},"suckIn":{"bones":{"hip":{"rotate":[{"time":0,"angle":-0.44},{"time":0.3333,"angle":5.03},{"time":4.3333,"angle":7.19},{"time":5.6666,"angle":24.09}],"translate":[{"time":0,"x":-1.63,"y":0},{"time":0.3333,"x":-177.04,"y":-13.11},{"time":0.7666,"x":-377.03,"y":-231.13},{"time":2.3333,"x":-403.3,"y":-231.13},{"time":2.4,"x":-406,"y":-231.13},{"time":2.6,"x":-450.8,"y":-231.13},{"time":2.8333,"x":-485.22,"y":-231.13},{"time":3.2333,"x":-485.22,"y":-169.99},{"time":5.3,"x":-485.22,"y":45.88},{"time":5.6666,"x":-481.48,"y":45.88},{"time":6,"x":2012.81,"y":45.88}]},"leftUpperLeg":{"rotate":[{"time":0,"angle":-0.44},{"time":0.3333,"angle":69.99},{"time":0.5333,"angle":96.39},{"time":0.7666,"angle":116.79},{"time":2.1666,"angle":126.82},{"time":3,"angle":133.33},{"time":3.9666,"angle":65.76},{"time":4.0333,"angle":64.03},{"time":4.1666,"angle":71.33},{"time":4.3333,"angle":50.39},{"time":4.9333,"angle":22.94},{"time":5.2333,"angle":93.48},{"time":5.6,"angle":140.29}]},"rightUpperLeg":{"rotate":[{"time":0,"angle":-0.44},{"time":0.3333,"angle":48.98},{"time":0.5333,"angle":91.11},{"time":0.7666,"angle":115.8},{"time":2,"angle":126.66},{"time":3,"angle":112.16},{"time":4.5,"angle":38.49},{"time":5.2333,"angle":65.41},{"time":5.6,"angle":134.2}]},"spine":{"rotate":[{"time":0,"angle":-0.44},{"time":0.3333,"angle":-16.94},{"time":0.6333,"angle":-2.08},{"time":0.7666,"angle":9.15},{"time":1.1666,"angle":27.34},{"time":2.4333,"angle":32.91},{"time":4.1666,"angle":51.34},{"time":5.6,"angle":26.29}]},"leftLowerLeg":{"rotate":[{"time":0,"angle":-0.44},{"time":0.3333,"angle":-27.5},{"time":0.5333,"angle":-19.04},{"time":0.7666,"angle":-72.63},{"time":2.1666,"angle":-130.05},{"time":2.4333,"angle":-88.16},{"time":2.6666,"angle":-131.38},{"time":2.8333,"angle":-102.54},{"time":3,"angle":-81.74},{"time":4.0333,"angle":-57.2},{"time":4.3333,"angle":-42.31},{"time":5.6,"angle":-110.45}]},"leftUpperArm":{"rotate":[{"time":0,"angle":-0.44},{"time":0.3333,"angle":104.28},{"time":0.6333,"angle":73.8},{"time":0.7666,"angle":31.82},{"time":1.1666,"angle":-1.34},{"time":1.5,"angle":303.25},{"time":1.8333,"angle":288.29},{"time":2.4333,"angle":271.87},{"time":2.5666,"angle":291.22},{"time":2.6666,"angle":327.48},{"time":3.1,"angle":40.38},{"time":4.7666,"angle":28.91},{"time":5.0666,"angle":-2.2},{"time":5.1333,"angle":336.11},{"time":5.2,"angle":356.38},{"time":5.6,"angle":29.73}]},"neck":{"rotate":[{"time":0,"angle":-0.44}]},"rightLowerLeg":{"rotate":[{"time":0,"angle":-0.44},{"time":0.3333,"angle":-27.71},{"time":0.5333,"angle":-30.42},{"time":0.7666,"angle":-67.71},{"time":2,"angle":-101.22},{"time":2.3333,"angle":-133.63},{"time":2.6,"angle":-96.97},{"time":3,"angle":-45.87},{"time":5.6,"angle":-101.2}]},"rightUpperArm":{"rotate":[{"time":0,"angle":359.55},{"time":0.3333,"angle":78.75},{"time":0.6333,"angle":82.82},{"time":0.7666,"angle":52.36},{"time":1.1666,"angle":0.29},{"time":1.5,"angle":324.61},{"time":1.8333,"angle":294.2},{"time":2,"angle":282.45},{"time":2.4333,"angle":316.17},{"time":2.6666,"angle":285.18},{"time":2.8333,"angle":339.1},{"time":3.2333,"angle":295.17},{"time":4.1666,"angle":30.43},{"time":4.7666,"angle":307.05},{"time":5.0666,"angle":298.59},{"time":5.4,"angle":1.3},{"time":5.6,"angle":36.69}],"translate":[{"time":0,"x":0.09,"y":-3.37}]},"head":{"rotate":[{"time":0,"angle":-0.44},{"time":0.3333,"angle":15.36},{"time":0.7666,"angle":-10.4}]},"leftFoot":{"rotate":[{"time":0,"angle":-0.44},{"time":0.3333,"angle":-14.59},{"time":0.7666,"angle":-5.35},{"time":3.7333,"angle":-10.87},{"time":3.9666,"angle":7.12},{"time":4.6666,"angle":-39.02}]},"leftLowerArm":{"rotate":[{"time":0,"angle":-0.44},{"time":0.3333,"angle":18.78},{"time":1.5,"angle":73.26},{"time":2.3333,"angle":87.4},{"time":2.6666,"angle":53.14},{"time":3.1,"angle":32.75},{"time":5.0666,"angle":18.74}]},"rightFoot":{"rotate":[{"time":0,"angle":-0.44},{"time":0.3333,"angle":-12.28},{"time":0.7666,"angle":-2.09},{"time":4.3333,"angle":-7.89},{"time":4.6666,"angle":-38.85}]},"rightLowerArm":{"rotate":[{"time":0,"angle":-0.44},{"time":0.3333,"angle":20.66},{"time":1.5,"angle":66.41},{"time":2,"angle":83.57},{"time":2.8333,"angle":43.72},{"time":5.0666,"angle":15.81},{"time":5.6,"angle":20.41}]},"leftHand":{"rotate":[{"time":0,"angle":-0.44}]},"rightHand":{"rotate":[{"time":0,"angle":-0.44}]}}},"upJump":{"bones":{"leftUpperLeg":{"rotate":[{"time":0,"angle":62.08},{"time":0.1666,"angle":45.45},{"time":0.3333,"angle":8.48},{"time":0.5,"angle":0.85}]},"rightUpperLeg":{"rotate":[{"time":0,"angle":-21.56},{"time":0.1666,"angle":19.04},{"time":0.3333,"angle":-0.38},{"time":0.5,"angle":-8.01}]},"spine":{"rotate":[{"time":0,"angle":-5.74}]},"leftLowerLeg":{"rotate":[{"time":0,"angle":-71.91},{"time":0.3333,"angle":-8.21},{"time":0.5,"angle":0.23}]},"leftUpperArm":{"rotate":[{"time":0,"angle":316.07},{"time":0.1666,"angle":99.02},{"time":0.3333,"angle":125.82},{"time":0.5,"angle":143.97}]},"rightLowerLeg":{"rotate":[{"time":0,"angle":-29.15},{"time":0.5,"angle":7.48}]},"rightUpperArm":{"rotate":[{"time":0,"angle":53.3},{"time":0.1666,"angle":110.31},{"time":0.3333,"angle":131.91},{"time":0.5,"angle":142.69}]},"head":{"rotate":[{"time":0,"angle":16.94},{"time":0.5,"angle":45.39}]},"leftLowerArm":{"rotate":[{"time":0,"angle":31.45},{"time":0.1666,"angle":45.21},{"time":0.5,"angle":20.63}]},"rightLowerArm":{"rotate":[{"time":0,"angle":24.03},{"time":0.5,"angle":19.33}]},"rightFoot":{"rotate":[{"time":0,"angle":7.76},{"time":0.3333,"angle":-27.85}]},"leftFoot":{"rotate":[{"time":0,"angle":4.52},{"time":0.3333,"angle":-25.09}]}},"slots":{"left hooked arm":{"attachment":[{"time":0,"name":null}]},"right hooked arm":{"attachment":[{"time":0,"name":null}]},"right open hand":{"attachment":[{"time":0,"name":null}]}}},"walking":{}}}