{"bones":[{"name":"root"},{"name":"hip","parent":"root","y":197.86},{"name":"lupperLeg","parent":"hip","length":70.97,"x":7.62,"y":0.2,"rotation":-81.07},{"name":"rupperLeg","parent":"hip","length":73.93,"x":-6.24,"y":1.84,"rotation":-101.83},{"name":"skirt","parent":"hip","length":85,"x":2.04,"y":-1.9,"rotation":-95.2},{"name":"spine","parent":"hip","length":178.15,"x":0.96,"y":6.91,"rotation":92.29},{"name":"frontSkirt","parent":"skirt","length":83.23,"x":-14.95,"y":32.85,"rotation":3},{"name":"lLeg","parent":"lupperLeg","length":94,"x":71.47,"y":-0.2,"rotation":-8.03},{"name":"lUpperArm","parent":"spine","length":78,"x":165.46,"y":-6.82,"rotation":177.59},{"name":"neck","parent":"spine","length":25.9,"x":176.3,"y":-11.85,"rotation":-16.17},{"name":"rLeg","parent":"rupperLeg","length":94,"x":74.36,"y":0.94,"rotation":12.82},{"name":"rUpperArm","parent":"spine","length":78,"x":167.53,"y":-8.74,"rotation":178.96},{"name":"head","parent":"neck","length":66.79,"x":24.47,"y":0.45,"rotation":-3.82},{"name":"lFoot","parent":"lLeg","length":47.16,"x":104.86,"y":0.99,"scaleX":-1,"rotation":-87.33},{"name":"lLowerArm","parent":"lUpperArm","length":75.53,"x":82.64,"y":-1.43,"rotation":14.11},{"name":"rFoot","parent":"rLeg","length":50,"x":103.1,"y":0.88,"scaleX":-1,"rotation":-90.87},{"name":"rLowerArm","parent":"rUpperArm","length":75.54,"x":82.07,"y":0.37,"rotation":11.48},{"name":"lHand","parent":"lLowerArm","length":23.47,"x":77.71,"y":-1.39,"rotation":-0.76},{"name":"rHand","parent":"rLowerArm","length":26.88,"x":89.63,"y":-1.51,"rotation":-4.5}],"slots":[{"name":"RFoot","bone":"rFoot","attachment":"RFoot"},{"name":"RLeg","bone":"rLeg","attachment":"RLeg"},{"name":"LLeg","bone":"lLeg","attachment":"LLeg"},{"name":"LFoot","bone":"lFoot","attachment":"LFoot"},{"name":"RLowerArm","bone":"rLowerArm","attachment":"RLowerArm"},{"name":"RupperArm","bone":"rUpperArm","attachment":"RupperArm"},{"name":"neck","bone":"neck","attachment":"neck"},{"name":"RHand","bone":"rHand","attachment":"RHand"},{"name":"torso","bone":"spine","attachment":"torso"},{"name":"frontSkirt","bone":"frontSkirt","attachment":"frontSkirt"},{"name":"skirt","bone":"skirt","attachment":"skirt"},{"name":"head","bone":"head","attachment":"head"},{"name":"LupperArm","bone":"lUpperArm","attachment":"LupperArm"},{"name":"LlowerrArm","bone":"lLowerArm","attachment":"LlowerrArm"},{"name":"LHand","bone":"lHand","attachment":"LHand"}],"skins":{"default":{"LFoot":{"LFoot":{"x":17.03,"y":7.99,"scaleX":0.35,"scaleY":0.346,"rotation":177.89,"width":189,"height":102}},"LHand":{"LHand":{"x":13.36,"y":0.1,"scaleX":0.356,"scaleY":-0.36,"rotation":-113.99,"width":77,"height":145}},"LLeg":{"LLeg":{"x":47.94,"y":0.55,"scaleX":-0.35,"scaleY":0.35,"rotation":97.99,"width":101,"height":316}},"LlowerrArm":{"LlowerrArm":{"x":36.83,"y":-3.54,"scaleX":0.401,"scaleY":-0.4,"rotation":-92.73,"width":66,"height":222}},"LupperArm":{"LupperArm":{"x":38.68,"y":-2.84,"scaleX":-0.34,"scaleY":0.339,"rotation":142.32,"width":249,"height":207}},"RFoot":{"RFoot":{"x":12.63,"y":7.53,"scaleX":0.35,"scaleY":0.353,"rotation":176.56,"width":179,"height":94}},"RHand":{"RHand":{"x":13.36,"y":-0.79,"scaleX":0.365,"scaleY":-0.37,"rotation":-176.99,"width":131,"height":66}},"RLeg":{"RLeg":{"x":45.91,"y":-0.73,"scaleX":-0.35,"scaleY":0.354,"rotation":87.87,"width":93,"height":317}},"RLowerArm":{"RLowerArm":{"x":41.12,"y":-0.01,"scaleX":0.4,"scaleY":-0.439,"rotation":-149.88,"width":246,"height":128}},"RupperArm":{"RupperArm":{"x":41.52,"y":0.1,"scaleX":-0.34,"scaleY":0.342,"rotation":89.11,"width":93,"height":298}},"frontSkirt":{"frontSkirt":{"x":59.73,"y":3.57,"scaleX":-0.41,"scaleY":0.4,"rotation":95.26,"width":204,"height":241}},"head":{"head":{"x":36.59,"y":-3.01,"scaleX":-0.32,"scaleY":0.315,"rotation":-71.88,"width":324,"height":328}},"neck":{"neck":{"x":11.15,"y":-4.81,"scaleX":-0.34,"scaleY":0.338,"rotation":-76.12,"width":169,"height":138}},"skirt":{"skirt":{"x":30.33,"y":-15.62,"scaleX":-0.35,"scaleY":0.354,"rotation":90.7,"width":338,"height":364}},"torso":{"torso":{"x":88.04,"y":-4.82,"scaleX":-0.35,"scaleY":0.349,"rotation":-93.12,"width":243,"height":565}}}},"animations":{"crawling":{"bones":{"lupperLeg":{"rotate":[{"time":0,"angle":19.85},{"time":0.2,"angle":-13.11},{"time":0.4,"angle":-36.69},{"time":0.7666,"angle":17.07}]},"rupperLeg":{"rotate":[{"time":0,"angle":-4.86},{"time":0.2,"angle":19.56},{"time":0.4,"angle":43.89},{"time":0.6,"angle":15.63},{"time":0.7666,"angle":-2.37}]},"spine":{"rotate":[{"time":0,"angle":-69.83},{"time":0.2,"angle":-66.53},{"time":0.4,"angle":-71.75},{"time":0.6,"angle":-67.75},{"time":0.7666,"angle":-69.83}]},"frontSkirt":{"rotate":[{"time":0,"angle":30.3},{"time":0.2,"angle":24.55},{"time":0.4,"angle":29.58},{"time":0.6333,"angle":18.86},{"time":0.7666,"angle":25.97}],"translate":[{"time":0,"x":-0.62,"y":-18.77},{"time":0.2,"x":-7.45,"y":-19.9},{"time":0.4,"x":-6.6,"y":-19.27},{"time":0.7666,"x":-4.68,"y":-17.83}]},"lLeg":{"rotate":[{"time":0,"angle":-107.23},{"time":0.2,"angle":-77.57},{"time":0.4,"angle":-53.31},{"time":0.7666,"angle":-105.76}]},"lUpperArm":{"rotate":[{"time":0,"angle":-316.44},{"time":0.4,"angle":-262.39},{"time":0.6,"angle":-297.29,"curve":[0.25,0,0.75,1]},{"time":0.7666,"angle":-316.44}]},"rLeg":{"rotate":[{"time":0,"angle":-83.91},{"time":0.2,"angle":-108.68},{"time":0.4,"angle":-133.28},{"time":0.6,"angle":-104},{"time":0.7666,"angle":-86.36}]},"rUpperArm":{"rotate":[{"time":0,"angle":-265.94},{"time":0.2,"angle":-285.04},{"time":0.4,"angle":-325.12},{"time":0.6,"angle":-273.19,"curve":[0.25,0,0.75,1]},{"time":0.7666,"angle":-265.94}]},"head":{"rotate":[{"time":0,"angle":52.69,"curve":"stepped"},{"time":0.7666,"angle":52.69}]},"lLowerArm":{"rotate":[{"time":0,"angle":29.18},{"time":0.2,"angle":44},{"time":0.4,"angle":-14.82},{"time":0.6,"angle":16.24,"curve":[0.25,0,0.75,1]},{"time":0.7666,"angle":29.18}]},"rLowerArm":{"rotate":[{"time":0,"angle":-6.81},{"time":0.2,"angle":-5.89},{"time":0.4,"angle":35.32},{"time":0.6,"angle":35.85},{"time":0.7666,"angle":-6.81}]},"lHand":{"rotate":[{"time":0,"angle":49.19,"curve":"stepped"},{"time":0.7666,"angle":49.19}]},"rHand":{"rotate":[{"time":0,"angle":61.87},{"time":0.2,"angle":66.04},{"time":0.7666,"angle":61.87}],"translate":[{"time":0.4,"x":-5.5,"y":2.19}]},"hip":{"translate":[{"time":0,"x":0,"y":-100.26,"curve":"stepped"},{"time":0.7666,"x":0,"y":-100.26}]},"skirt":{"rotate":[{"time":0,"angle":-31.65,"curve":"stepped"},{"time":0.7666,"angle":-31.65}]}}},"idle":{},"jumping":{"bones":{"lUpperArm":{"rotate":[{"time":0,"angle":-4.87},{"time":0.1,"angle":-333.71},{"time":0.2333,"angle":-302.69},{"time":0.3,"angle":-254.24},{"time":0.3666,"angle":-236.8}]},"lLowerArm":{"rotate":[{"time":0,"angle":34.9},{"time":0.2333,"angle":48.98},{"time":0.5,"angle":27.45}]},"head":{"rotate":[{"time":0,"angle":-1.25},{"time":0.2333,"angle":18.47}]},"lupperLeg":{"rotate":[{"time":0,"angle":-5.84},{"time":0.1,"angle":30.42},{"time":0.2,"angle":4.33},{"time":0.3,"angle":-1.53}]},"rupperLeg":{"rotate":[{"time":0,"angle":3.29},{"time":0.1,"angle":35.39},{"time":0.2,"angle":16.81},{"time":0.3,"angle":11.74}]},"rLeg":{"rotate":[{"time":0,"angle":-11.83},{"time":0.1,"angle":-76.11},{"time":0.2,"angle":-40.27},{"time":0.3,"angle":-27.61}]},"lLeg":{"rotate":[{"time":0,"angle":-2.03},{"time":0.1,"angle":-67.5},{"time":0.2,"angle":-21.59},{"time":0.3,"angle":-7.67}]},"hip":{"translate":[{"time":0,"x":0,"y":1.87},{"time":0.1,"x":0,"y":-30.06},{"time":0.2,"x":0,"y":5.63},{"time":0.3,"x":0,"y":37.58}]},"lFoot":{"rotate":[{"time":0,"angle":3.48},{"time":0.2333,"angle":-11.44},{"time":0.2666,"angle":-21.9}]},"rFoot":{"rotate":[{"time":0,"angle":7.13},{"time":0.2333,"angle":0.94},{"time":0.2666,"angle":-13.11}]},"rUpperArm":{"rotate":[{"time":0,"angle":-39.43},{"time":0.2333,"angle":-351.74},{"time":0.4333,"angle":-332.28}]},"rLowerArm":{"rotate":[{"time":0,"angle":51.76},{"time":0.4333,"angle":35.74}]}}},"lieDown":{"bones":{"hip":{"rotate":[{"time":0,"angle":0.42}],"translate":[{"time":0,"x":0,"y":0},{"time":0.3,"x":0,"y":-4.44},{"time":0.3666,"x":0,"y":-13.33},{"time":0.4666,"x":0,"y":-62.24},{"time":0.5666,"x":0,"y":-100.77}]},"lupperLeg":{"rotate":[{"time":0,"angle":0.42},{"time":0.2333,"angle":12.57},{"time":0.4333,"angle":43.79},{"time":0.5333,"angle":29.26},{"time":0.6333,"angle":-4.78}]},"rupperLeg":{"rotate":[{"time":0,"angle":0.42},{"time":0.1,"angle":9.56},{"time":0.2333,"angle":14.88},{"time":0.5333,"angle":2.39},{"time":0.6333,"angle":7.2}]},"skirt":{"rotate":[{"time":0,"angle":0.42},{"time":0.3666,"angle":-34.56}]},"spine":{"rotate":[{"time":0,"angle":0.42},{"time":0.1,"angle":-8.46},{"time":0.1666,"angle":-24.95},{"time":0.2333,"angle":-34.91},{"time":0.3333,"angle":-50.99},{"time":0.5333,"angle":-64.02},{"time":0.6333,"angle":-69.83}]},"frontSkirt":{"rotate":[{"time":0,"angle":0.42},{"time":0.6333,"angle":16.54}]},"lLeg":{"rotate":[{"time":0,"angle":0.42},{"time":0.2333,"angle":-20.34},{"time":0.4333,"angle":-75.56},{"time":0.5333,"angle":-91.21},{"time":0.6333,"angle":-85.08}]},"lUpperArm":{"rotate":[{"time":0,"angle":0.42},{"time":0.3333,"angle":-321.3},{"time":0.5333,"angle":-305.25},{"time":0.6333,"angle":-300.5}]},"neck":{"rotate":[{"time":0,"angle":0.42}]},"rLeg":{"rotate":[{"time":0,"angle":0.42},{"time":0.1,"angle":-19.76},{"time":0.2333,"angle":-57.6},{"time":0.4333,"angle":-83.53},{"time":0.6333,"angle":-96.6}]},"rUpperArm":{"rotate":[{"time":0,"angle":0.42},{"time":0.1,"angle":-349.55},{"time":0.2333,"angle":-331.58},{"time":0.5333,"angle":-321.36},{"time":0.6333,"angle":-294.56}]},"head":{"rotate":[{"time":0,"angle":0.42},{"time":0.5,"angle":24.43},{"time":0.6333,"angle":52.69}]},"lFoot":{"rotate":[{"time":0,"angle":0.42}]},"lLowerArm":{"rotate":[{"time":0,"angle":0.42},{"time":0.6333,"angle":26.1}]},"rFoot":{"rotate":[{"time":0,"angle":0.42}]},"rLowerArm":{"rotate":[{"time":0,"angle":0.42},{"time":0.5333,"angle":20.76},{"time":0.6333,"angle":25.84}]},"lHand":{"rotate":[{"time":0,"angle":3.82},{"time":0.6333,"angle":37.93}]},"rHand":{"rotate":[{"time":0,"angle":3.76},{"time":0.6333,"angle":49.04}]}}},"lyingDown":{"bones":{"lupperLeg":{"rotate":[{"time":0,"angle":19.85}]},"rupperLeg":{"rotate":[{"time":0,"angle":-4.86}]},"spine":{"rotate":[{"time":0,"angle":-69.83}]},"frontSkirt":{"rotate":[{"time":0,"angle":30.3}],"translate":[{"time":0,"x":-0.62,"y":-18.77}]},"lLeg":{"rotate":[{"time":0,"angle":-107.23}]},"lUpperArm":{"rotate":[{"time":0,"angle":-316.44}]},"rLeg":{"rotate":[{"time":0,"angle":-83.91}]},"rUpperArm":{"rotate":[{"time":0,"angle":-265.94}]},"head":{"rotate":[{"time":0,"angle":52.69}]},"lLowerArm":{"rotate":[{"time":0,"angle":29.18}]},"rLowerArm":{"rotate":[{"time":0,"angle":-6.81}]},"lHand":{"rotate":[{"time":0,"angle":49.19}]},"rHand":{"rotate":[{"time":0,"angle":61.87}]},"hip":{"translate":[{"time":0,"x":0,"y":-100.26}]},"skirt":{"rotate":[{"time":0,"angle":-31.65}]}}},"pullUp":{"bones":{"lUpperArm":{"rotate":[{"time":0,"angle":-235},{"time":0.1666,"angle":-222.29},{"time":0.2666,"angle":-211.07},{"time":1.0333,"angle":-214.87},{"time":1.2,"angle":-222.81}]},"lLowerArm":{"rotate":[{"time":0,"angle":21.44},{"time":0.1666,"angle":-1.13}]},"head":{"rotate":[{"time":0,"angle":15.99}],"translate":[{"time":0,"x":2.77,"y":0.59}]},"lupperLeg":{"rotate":[{"time":0,"angle":1.91},{"time":0.2333,"angle":31.33},{"time":0.4333,"angle":43.81}]},"rupperLeg":{"rotate":[{"time":0,"angle":9.54},{"time":0.2333,"angle":22.51},{"time":0.4333,"angle":48.78},{"time":0.6,"angle":74.94},{"time":1.0333,"angle":58.9}]},"rLeg":{"rotate":[{"time":0,"angle":-28.31},{"time":0.5,"angle":-47.45},{"time":0.7666,"angle":-28.88},{"time":0.9,"angle":-57.02},{"time":1.4,"angle":-107.2}]},"lLeg":{"rotate":[{"time":0,"angle":-5.6},{"time":0.5,"angle":-3.58},{"time":0.7666,"angle":-53.04},{"time":0.9,"angle":4.13},{"time":1.0333,"angle":-26.02},{"time":1.4,"angle":-62.68}]},"hip":{"rotate":[{"time":0,"angle":-4.03},{"time":0.5,"angle":9.29}],"translate":[{"time":0,"x":0,"y":43.25}]},"lFoot":{"rotate":[{"time":0,"angle":-22.85},{"time":0.4333,"angle":-2.7}]},"rFoot":{"rotate":[{"time":0,"angle":-14.23},{"time":0.4333,"angle":3.89}]},"rUpperArm":{"rotate":[{"time":0,"angle":-331.01},{"time":0.1666,"angle":-228.27},{"time":0.3666,"angle":-217.04},{"time":1.0333,"angle":-220.84},{"time":1.2,"angle":-228.79}]},"rLowerArm":{"rotate":[{"time":0,"angle":38.02},{"time":0.1333,"angle":65.37},{"time":0.2333,"angle":11.46}]},"spine":{"rotate":[{"time":0,"angle":1.78},{"time":0.5,"angle":-10.09}]},"frontSkirt":{"rotate":[{"time":0,"angle":2.74},{"time":0.4333,"angle":16.01}]}}},"running":{"bones":{"hip":{"translate":[{"time":0,"x":0,"y":14.12},{"time":0.1,"x":0,"y":19.14},{"time":0.3666,"x":0,"y":-7.24},{"time":0.6333,"x":0,"y":18.43},{"time":0.9,"x":0,"y":1.31},{"time":1.0333,"x":0,"y":2.74},{"time":1.0666,"x":0,"y":6.3},{"time":1.1333,"x":0,"y":14.12}]},"lupperLeg":{"rotate":[{"time":0,"angle":47.6},{"time":0.1,"angle":36.01},{"time":0.2333,"angle":16.78},{"time":0.3666,"angle":-1.83},{"time":0.5,"angle":-36.62},{"time":0.6333,"angle":-29.93},{"time":0.7666,"angle":-12.98},{"time":0.9,"angle":6.87},{"time":1.0333,"angle":27.13},{"time":1.1333,"angle":47.6}]},"rupperLeg":{"rotate":[{"time":0,"angle":-14.65},{"time":0.1,"angle":3},{"time":0.2333,"angle":26.9},{"time":0.3666,"angle":46.35},{"time":0.5,"angle":74.74},{"time":0.6333,"angle":70.77},{"time":0.7666,"angle":49.8},{"time":0.9,"angle":29.18},{"time":1.0333,"angle":19.42},{"time":1.1333,"angle":-14.65}],"translate":[{"time":0,"x":-2.46,"y":-2.1,"curve":"stepped"},{"time":1.1333,"x":-2.46,"y":-2.1}]},"lLeg":{"rotate":[{"time":0,"angle":-49.1},{"time":0.1,"angle":-23.93},{"time":0.3666,"angle":-9.06},{"time":0.5,"angle":-12.79},{"time":0.6333,"angle":-28.95},{"time":0.7666,"angle":-73.8},{"time":0.9,"angle":-80.3},{"time":1.1333,"angle":-49.1}]},"lUpperArm":{"rotate":[{"time":0,"angle":-58.98},{"time":0.0666,"angle":-52.21},{"time":0.1,"angle":-42.53},{"time":0.2333,"angle":-8.08},{"time":0.3666,"angle":-345.25},{"time":0.6333,"angle":-318.19},{"time":1.1333,"angle":-58.98}]},"rLeg":{"rotate":[{"time":0,"angle":-36.33},{"time":0.1,"angle":-79.7},{"time":0.2333,"angle":-98.91},{"time":0.3666,"angle":-96.07},{"time":0.5,"angle":-76.54},{"time":0.6333,"angle":-55.87},{"time":0.7666,"angle":-32.79},{"time":0.9,"angle":-31.41},{"time":1.1333,"angle":-36.33}]},"rUpperArm":{"rotate":[{"time":0,"angle":-333.14},{"time":0.1,"angle":-352.95},{"time":0.2333,"angle":-358.04},{"time":0.3666,"angle":-8.43},{"time":0.5,"angle":-51.24},{"time":0.6333,"angle":-65.49},{"time":1.1333,"angle":-333.14}],"translate":[{"time":0,"x":-0.79,"y":-19.71,"curve":"stepped"},{"time":1.1333,"x":-0.79,"y":-19.71}]},"lFoot":{"rotate":[{"time":0,"angle":4.76},{"time":0.3666,"angle":7.17},{"time":1.1333,"angle":4.76}]},"lLowerArm":{"rotate":[{"time":0,"angle":71.98},{"time":0.0666,"angle":62.48},{"time":0.3666,"angle":48.31},{"time":1.1333,"angle":71.98}]},"rLowerArm":{"rotate":[{"time":0,"angle":79.84},{"time":0.2333,"angle":54.26},{"time":0.3666,"angle":22.52},{"time":0.5,"angle":40.52},{"time":0.6333,"angle":64.66},{"time":1.1333,"angle":79.84}]},"head":{"rotate":[{"time":0,"angle":0.38},{"time":0.3666,"angle":-5.79},{"time":0.6333,"angle":-2.68},{"time":0.9,"angle":-5.86},{"time":1.1333,"angle":0.38}]},"lHand":{"rotate":[{"time":0,"angle":14.98,"curve":"stepped"},{"time":1.1333,"angle":14.98}]},"rHand":{"rotate":[{"time":0,"angle":60.09},{"time":0.6333,"angle":45.02},{"time":1.1333,"angle":60.09}]},"frontSkirt":{"rotate":[{"time":0,"angle":14.82},{"time":0.1,"angle":6.34},{"time":0.2333,"angle":-7.95},{"time":0.5,"angle":17.66},{"time":0.6333,"angle":14.74},{"time":0.7666,"angle":-2.44},{"time":1.1333,"angle":14.82}]},"spine":{"rotate":[{"time":0,"angle":-7.31,"curve":"stepped"},{"time":1.1333,"angle":-7.31}]},"skirt":{"rotate":[{"time":0,"angle":1.35,"curve":"stepped"},{"time":1.1333,"angle":1.35}]},"rFoot":{"rotate":[{"time":1.0333,"angle":8.97},{"time":1.1333,"angle":4.34}]}}},"standUp":{"bones":{"hip":{"rotate":[{"time":0.7333,"angle":0.42}],"translate":[{"time":0,"x":0,"y":-108.66},{"time":0.0666,"x":0,"y":-100.77},{"time":0.1666,"x":0,"y":-68.6},{"time":0.2333,"x":0,"y":-62.24},{"time":0.3333,"x":0,"y":-13.33},{"time":0.4666,"x":0,"y":-4.44},{"time":0.7333,"x":0,"y":0}]},"lupperLeg":{"rotate":[{"time":0,"angle":-4.78},{"time":0.1,"angle":29.26},{"time":0.3,"angle":43.79},{"time":0.5333,"angle":12.57},{"time":0.7333,"angle":0.42}]},"rupperLeg":{"rotate":[{"time":0,"angle":7.2},{"time":0.1,"angle":2.39},{"time":0.5333,"angle":14.88},{"time":0.6333,"angle":9.56},{"time":0.7333,"angle":0.42}]},"skirt":{"rotate":[{"time":0,"angle":-43.4},{"time":0.3333,"angle":-34.56},{"time":0.7333,"angle":0.42}]},"spine":{"rotate":[{"time":0,"angle":-69.83},{"time":0.1,"angle":-64.02},{"time":0.4,"angle":-50.99},{"time":0.5333,"angle":-34.91},{"time":0.5666,"angle":-24.95},{"time":0.6333,"angle":-8.46},{"time":0.7333,"angle":0.42}]},"frontSkirt":{"rotate":[{"time":0,"angle":16.54},{"time":0.7333,"angle":0.42}]},"lLeg":{"rotate":[{"time":0,"angle":-85.08},{"time":0.1,"angle":-91.21},{"time":0.3,"angle":-75.56},{"time":0.5333,"angle":-20.34},{"time":0.7333,"angle":0.42}]},"lUpperArm":{"rotate":[{"time":0,"angle":-300.5},{"time":0.1,"angle":-305.25},{"time":0.4,"angle":-321.3},{"time":0.7333,"angle":0.42}]},"neck":{"rotate":[{"time":0.7333,"angle":0.42}]},"rLeg":{"rotate":[{"time":0,"angle":-96.6},{"time":0.3,"angle":-83.53},{"time":0.5333,"angle":-57.6},{"time":0.6333,"angle":-19.76},{"time":0.7333,"angle":0.42}]},"rUpperArm":{"rotate":[{"time":0,"angle":-294.56},{"time":0.1,"angle":-321.36},{"time":0.5333,"angle":-331.58},{"time":0.6333,"angle":-349.55},{"time":0.7333,"angle":0.42}]},"head":{"rotate":[{"time":0,"angle":52.69},{"time":0.1666,"angle":24.43},{"time":0.7333,"angle":0.42}]},"lFoot":{"rotate":[{"time":0.7333,"angle":0.42}]},"lLowerArm":{"rotate":[{"time":0,"angle":26.1},{"time":0.7333,"angle":0.42}]},"rFoot":{"rotate":[{"time":0.7333,"angle":0.42}]},"rLowerArm":{"rotate":[{"time":0,"angle":25.84},{"time":0.1,"angle":20.76},{"time":0.7333,"angle":0.42}]},"lHand":{"rotate":[{"time":0,"angle":37.93},{"time":0.7333,"angle":3.82}]},"rHand":{"rotate":[{"time":0,"angle":49.04},{"time":0.7333,"angle":3.76}]}}},"suckIn":{"bones":{"hip":{"rotate":[{"time":5.3333,"angle":-21.16}],"translate":[{"time":0,"x":-5.8,"y":0},{"time":0.1,"x":-42.49,"y":0},{"time":0.3,"x":-118.16,"y":0},{"time":0.5,"x":-191.53,"y":0},{"time":1.3333,"x":-192.86,"y":0},{"time":2.8333,"x":-188.89,"y":0},{"time":5,"x":-191,"y":97.92},{"time":5.3333,"x":-191.53,"y":92.63},{"time":5.6666,"x":1862.42,"y":0}]},"lUpperArm":{"rotate":[{"time":0,"angle":-349.16},{"time":0.1,"angle":-309.76},{"time":0.1666,"angle":-285.72},{"time":0.2333,"angle":-261.56},{"time":0.5,"angle":-275.25},{"time":0.9,"angle":-344.64},{"time":1,"angle":-339.94},{"time":1.1666,"angle":-4.76},{"time":1.5,"angle":-12.13},{"time":5,"angle":-299.63},{"time":5.1666,"angle":-317.86},{"time":5.3333,"angle":-269.32}]},"rUpperArm":{"rotate":[{"time":0,"angle":-355.61},{"time":0.1,"angle":-290.11},{"time":0.1666,"angle":-283.83},{"time":0.3,"angle":-300.39},{"time":0.7666,"angle":-315.46},{"time":0.8666,"angle":-349.64},{"time":1.5,"angle":-9.43},{"time":3,"angle":-6.83},{"time":5.1666,"angle":-310.76},{"time":5.3333,"angle":-243.84}]},"rLowerArm":{"rotate":[{"time":0,"angle":4.73},{"time":0.1,"angle":55.94},{"time":0.1666,"angle":75.62},{"time":0.2333,"angle":38.8},{"time":0.3,"angle":69.05},{"time":0.6,"angle":62.06},{"time":1.1666,"angle":60.45},{"time":1.3333,"angle":23.67},{"time":1.5,"angle":2.14}]},"lLowerArm":{"rotate":[{"time":0,"angle":7.64},{"time":0.1,"angle":31.37},{"time":0.1666,"angle":47.48},{"time":0.2333,"angle":20.23},{"time":0.3,"angle":49.7},{"time":0.5,"angle":77.38},{"time":1.1666,"angle":28.87},{"time":1.5,"angle":7.38}]},"spine":{"rotate":[{"time":0,"angle":0},{"time":0.1666,"angle":8.52},{"time":5,"angle":4.81},{"time":5.1666,"angle":-1.33},{"time":5.3333,"angle":-22.3}]},"neck":{"rotate":[{"time":0,"angle":-1.3},{"time":0.1666,"angle":-15.07}]},"rupperLeg":{"rotate":[{"time":0,"angle":-0.43},{"time":0.1333,"angle":23.12},{"time":0.1666,"angle":21.83},{"time":0.3333,"angle":13.16},{"time":0.4,"angle":27.28},{"time":0.4666,"angle":31.09},{"time":3.6666,"angle":26.79},{"time":3.8333,"angle":13.95},{"time":4,"angle":36.23},{"time":4.3333,"angle":51.13},{"time":4.5,"angle":29.67},{"time":5.1666,"angle":27.81},{"time":5.3333,"angle":-11.59}]},"lupperLeg":{"rotate":[{"time":0,"angle":-3.85},{"time":0.1666,"angle":-9.36},{"time":0.2333,"angle":-13.79},{"time":0.3333,"angle":1.69},{"time":0.4,"angle":-11.32},{"time":3.6666,"angle":-3.4},{"time":3.8333,"angle":24.03},{"time":4,"angle":-6.97},{"time":4.3333,"angle":-15.79},{"time":4.5,"angle":13.43},{"time":5,"angle":-11.32},{"time":5.3333,"angle":-54.67}]},"rFoot":{"rotate":[{"time":0,"angle":-0.88},{"time":0.1666,"angle":-5.12}]},"rLeg":{"rotate":[{"time":0,"angle":-2.98},{"time":0.3333,"angle":-55.28},{"time":0.4,"angle":-39.87},{"time":0.4666,"angle":-28.58},{"time":3.8333,"angle":-58.54},{"time":5.3333,"angle":-41.9}]},"lLeg":{"rotate":[{"time":0,"angle":0.79},{"time":0.1333,"angle":-40.25},{"time":0.2333,"angle":-12.25},{"time":0.3,"angle":2.09},{"time":0.3333,"angle":-3.7},{"time":0.4,"angle":-16.3},{"time":0.4666,"angle":-26.41},{"time":1.1666,"angle":-19.93},{"time":1.3333,"angle":1.56},{"time":3.8333,"angle":-35.63},{"time":4.3333,"angle":-19.23},{"time":5,"angle":1.56},{"time":5.3333,"angle":-26.09}]},"head":{"rotate":[{"time":0,"angle":-4.78},{"time":0.1666,"angle":1.63},{"time":0.3333,"angle":6.37},{"time":0.5,"angle":12.01},{"time":0.6666,"angle":26.23},{"time":1,"angle":39.76},{"time":3,"angle":27.74},{"time":4.3333,"angle":-8.98},{"time":5,"angle":6.33}]},"skirt":{"rotate":[{"time":0,"angle":-0.44},{"time":3.0333,"angle":-0.77},{"time":5.3333,"angle":-28.07}],"translate":[{"time":0,"x":0,"y":4.2},{"time":3.0333,"x":-2.2,"y":13.22},{"time":3.3,"x":-2.2,"y":25.84}]},"frontSkirt":{"rotate":[{"time":0,"angle":-2.73},{"time":2.6666,"angle":6.61},{"time":3.0333,"angle":19.14}],"translate":[{"time":0,"x":2.09,"y":0.2},{"time":3.0333,"x":0.74,"y":-5.08}]}}},"upJump":{"bones":{"lUpperArm":{"rotate":[{"time":0,"angle":-4.87},{"time":0.1,"angle":-333.71},{"time":0.2333,"angle":-302.69},{"time":0.3,"angle":-254.24},{"time":0.3666,"angle":-217.05}]},"lLowerArm":{"rotate":[{"time":0,"angle":34.9},{"time":0.2333,"angle":48.98},{"time":0.3666,"angle":3.9},{"time":0.5,"angle":5.41}]},"head":{"rotate":[{"time":0,"angle":-1.25},{"time":0.2333,"angle":18.47}]},"lupperLeg":{"rotate":[{"time":0,"angle":-5.84},{"time":0.1,"angle":43.81},{"time":0.2,"angle":4.33},{"time":0.3,"angle":-1.53}]},"rupperLeg":{"rotate":[{"time":0,"angle":3.29},{"time":0.1,"angle":49.52},{"time":0.2,"angle":16.81},{"time":0.3,"angle":11.74}]},"rLeg":{"rotate":[{"time":0,"angle":-11.83},{"time":0.1,"angle":-93.03},{"time":0.2,"angle":-40.27},{"time":0.3,"angle":-27.61},{"time":0.3666,"angle":-18.19}]},"lLeg":{"rotate":[{"time":0,"angle":-2.03},{"time":0.1,"angle":-83.21},{"time":0.2,"angle":-21.59},{"time":0.3,"angle":-7.67}]},"hip":{"translate":[{"time":0,"x":0,"y":1.87},{"time":0.1,"x":0,"y":-51.31},{"time":0.2,"x":0,"y":5.63},{"time":0.3,"x":0,"y":37.58}]},"lFoot":{"rotate":[{"time":0,"angle":3.48},{"time":0.1,"angle":25.61},{"time":0.2333,"angle":-11.44},{"time":0.3,"angle":-40.18}]},"rFoot":{"rotate":[{"time":0,"angle":7.13},{"time":0.1,"angle":33.79},{"time":0.2333,"angle":0.94},{"time":0.2666,"angle":-35.71}]},"rUpperArm":{"rotate":[{"time":0,"angle":-39.43},{"time":0.2333,"angle":-351.74},{"time":0.4333,"angle":0.82}]},"rLowerArm":{"rotate":[{"time":0,"angle":51.76},{"time":0.4333,"angle":21.53}]},"neck":{"rotate":[{"time":0.1666,"angle":-3.91},{"time":0.3666,"angle":20.09}]}}},"walking":{"bones":{"hip":{"translate":[{"time":0,"x":0,"y":-10.13},{"time":0.1333,"x":0,"y":-9.71},{"time":0.2666,"x":0,"y":-3.56},{"time":0.4,"x":0,"y":-1.57},{"time":0.5333,"x":0,"y":-11.5},{"time":0.6666,"x":0,"y":-14.34},{"time":0.8,"x":0,"y":-5.75},{"time":1.0666,"x":0,"y":3.23},{"time":1.2666,"x":0,"y":-10.13}]},"lupperLeg":{"rotate":[{"time":0,"angle":19.96},{"time":0.1333,"angle":13.72},{"time":0.2666,"angle":1.04},{"time":0.4,"angle":-3.56},{"time":0.5333,"angle":-22.22},{"time":0.6666,"angle":-8.65},{"time":0.8,"angle":-1.23},{"time":0.9333,"angle":26.06},{"time":1.0666,"angle":19.89},{"time":1.2666,"angle":21.81}],"translate":[{"time":0.0333,"x":0,"y":1.25},{"time":0.0666,"x":0,"y":3.54},{"time":0.1,"x":0,"y":4.8},{"time":0.1333,"x":0,"y":4.57},{"time":0.4666,"x":0,"y":-4.2},{"time":0.5,"x":0,"y":-7.36},{"time":0.5333,"x":0,"y":-10.51},{"time":0.8666,"x":0,"y":0.78},{"time":1.0666,"x":0,"y":-8.87},{"time":1.1333,"x":0,"y":-5.19},{"time":1.2666,"x":0,"y":1.05}]},"rupperLeg":{"rotate":[{"time":0,"angle":-2.17},{"time":0.1333,"angle":12.32},{"time":0.2666,"angle":28.77},{"time":0.4,"angle":58.4},{"time":0.5333,"angle":45.98},{"time":0.6666,"angle":50.08},{"time":1.0666,"angle":2.14},{"time":1.2666,"angle":-2.17}],"translate":[{"time":0,"x":-2.46,"y":-2.1},{"time":1.2666,"x":-2.46,"y":-4.2}]},"lLeg":{"rotate":[{"time":0,"angle":-25.61},{"time":0.1333,"angle":-20.79},{"time":0.2666,"angle":-13.68},{"time":0.6666,"angle":-53.15},{"time":0.8,"angle":-58.45},{"time":0.9333,"angle":-48.65},{"time":1.0666,"angle":-7.19},{"time":1.1333,"angle":-16.49},{"time":1.2666,"angle":-25.61}]},"lUpperArm":{"rotate":[{"time":0,"angle":-28.88},{"time":0.6666,"angle":-349.9},{"time":1.2666,"angle":-28.32}]},"rLeg":{"rotate":[{"time":0,"angle":-47.7},{"time":0.1333,"angle":-70.91},{"time":0.2666,"angle":-91.9},{"time":0.4,"angle":-64.35},{"time":0.5333,"angle":-21.13},{"time":0.6666,"angle":-49.18},{"time":0.8,"angle":-43.5},{"time":1.2666,"angle":-47.7}]},"rUpperArm":{"rotate":[{"time":0,"angle":-356.58},{"time":0.6666,"angle":-34.46},{"time":1.2666,"angle":-355.44}],"translate":[{"time":0,"x":-0.79,"y":-19.71,"curve":"stepped"},{"time":1.2666,"x":-0.79,"y":-19.71}]},"lFoot":{"rotate":[{"time":0,"angle":4.76},{"time":0.1,"angle":2.23},{"time":0.1333,"angle":3.73},{"time":0.2666,"angle":-2.1},{"time":0.4,"angle":15.23},{"time":1.0666,"angle":9.5},{"time":1.2666,"angle":0}]},"rFoot":{"rotate":[{"time":0.7,"angle":2.25},{"time":0.7333,"angle":5.89},{"time":0.7666,"angle":4.51},{"time":0.8,"angle":6.73},{"time":1.2666,"angle":2.99}]},"lLowerArm":{"rotate":[{"time":0,"angle":32.72},{"time":0.6666,"angle":2.57},{"time":1.2666,"angle":33.25}]},"rLowerArm":{"rotate":[{"time":0,"angle":13.04},{"time":0.1333,"angle":23.82},{"time":0.6666,"angle":37.43},{"time":1.2666,"angle":13.04}]},"head":{"rotate":[{"time":0,"angle":-8.92},{"time":0.4,"angle":-2.89},{"time":0.6666,"angle":-8.21},{"time":0.9333,"angle":-4.12},{"time":1.0666,"angle":-4.27},{"time":1.2666,"angle":-7.64}]},"lHand":{"rotate":[{"time":0,"angle":14.98}]},"rHand":{"rotate":[{"time":0,"angle":10.39}]},"frontSkirt":{"rotate":[{"time":0,"angle":-5.52},{"time":0.1333,"angle":-12.56},{"time":0.2666,"angle":-15.69},{"time":0.4,"angle":3.06},{"time":0.5333,"angle":-6.34},{"time":0.6666,"angle":-2.93},{"time":0.8,"angle":-16.46},{"time":0.9333,"angle":-11.1},{"time":1.0666,"angle":-5.18},{"time":1.2,"angle":-2.79}]}}}}}